[
  {
    "time": "2025-08-14 13:00",
    "temp": 21.9,
    "desc": "lätt molnighet"
  },
  {
    "time": "2025-08-14 14:00",
    "temp": 21.7,
    "desc": "lätt molnighet"
  },
  {
    "time": "2025-08-14 15:00",
    "temp": 21.4,
    "desc": "lätt molnighet"
  },
  {
    "time": "2025-08-14 16:00",
    "temp": 20.7,
    "desc": "lätt molnighet"
  },
  {
    "time": "2025-08-14 17:00",
    "temp": 19.9,
    "desc": "lätt molnighet"
  },
  {
    "time": "2025-08-14 18:00",
    "temp": 18.9,
    "desc": "lätt molnighet"
  },
  {
    "time": "2025-08-14 19:00",
    "temp": 17.6,
    "desc": "lätt molnighet"
  },
  {
    "time": "2025-08-14 20:00",
    "temp": 16.9,
    "desc": "regn"
  },
  {
    "time": "2025-08-14 21:00",
    "temp": 16.6,
    "desc": "regn"
  },
  {
    "time": "2025-08-14 22:00",
    "temp": 16.6,
    "desc": "regn"
  },
  {
    "time": "2025-08-14 23:00",
    "temp": 16.1,
    "desc": "regn"
  },
  {
    "time": "2025-08-15 00:00",
    "temp": 15.6,
    "desc": "regn"
  },
  {
    "time": "2025-08-15 01:00",
    "temp": 15.3,
    "desc": "halvklart"
  },
  {
    "time": "2025-08-15 02:00",
    "temp": 15.1,
    "desc": "halvklart"
  },
  {
    "time": "2025-08-15 03:00",
    "temp": 15.1,
    "desc": "molnigt"
  },
  {
    "time": "2025-08-15 04:00",
    "temp": 16.0,
    "desc": "molnigt"
  },
  {
    "time": "2025-08-15 05:00",
    "temp": 18.0,
    "desc": null
  },
  {
    "time": "2025-08-15 06:00",
    "temp": 19.2,
    "desc": "dimma"
  },
  {
    "time": "2025-08-15 07:00",
    "temp": 20.1,
    "desc": null
  },
  {
    "time": "2025-08-15 08:00",
    "temp": 20.1,
    "desc": null
  },
  {
    "time": "2025-08-15 09:00",
    "temp": 18.6,
    "desc": null
  },
  {
    "time": "2025-08-15 10:00",
    "temp": 18.0,
    "desc": null
  },
  {
    "time": "2025-08-15 11:00",
    "temp": 18.7,
    "desc": null
  },
  {
    "time": "2025-08-15 12:00",
    "temp": 18.8,
    "desc": "molnigt"
  },
  {
    "time": "2025-08-15 13:00",
    "temp": 18.7,
    "desc": "molnigt"
  },
  {
    "time": "2025-08-15 14:00",
    "temp": 18.8,
    "desc": "regn"
  },
  {
    "time": "2025-08-15 15:00",
    "temp": 17.9,
    "desc": null
  },
  {
    "time": "2025-08-15 16:00",
    "temp": 18.2,
    "desc": null
  },
  {
    "time": "2025-08-15 17:00",
    "temp": 16.1,
    "desc": null
  },
  {
    "time": "2025-08-15 18:00",
    "temp": 14.5,
    "desc": null
  },
  {
    "time": "2025-08-15 19:00",
    "temp": 13.8,
    "desc": null
  },
  {
    "time": "2025-08-15 20:00",
    "temp": 13.0,
    "desc": "regn"
  },
  {
    "time": "2025-08-15 21:00",
    "temp": 12.6,
    "desc": "regn"
  },
  {
    "time": "2025-08-15 22:00",
    "temp": 12.4,
    "desc": "regn"
  },
  {
    "time": "2025-08-15 23:00",
    "temp": 11.6,
    "desc": "lätt molnighet"
  },
  {
    "time": "2025-08-16 00:00",
    "temp": 10.5,
    "desc": "lätt molnighet"
  },
  {
    "time": "2025-08-16 01:00",
    "temp": 10.0,
    "desc": "halvklart"
  },
  {
    "time": "2025-08-16 02:00",
    "temp": 10.3,
    "desc": "halvklart"
  },
  {
    "time": "2025-08-16 03:00",
    "temp": 9.8,
    "desc": "halvklart"
  },
  {
    "time": "2025-08-16 04:00",
    "temp": 11.0,
    "desc": "regn"
  },
  {
    "time": "2025-08-16 05:00",
    "temp": 11.5,
    "desc": "regn"
  },
  {
    "time": "2025-08-16 06:00",
    "temp": 11.0,
    "desc": "kraftigt regn"
  },
  {
    "time": "2025-08-16 07:00",
    "temp": 10.8,
    "desc": "kraftigt regn"
  },
  {
    "time": "2025-08-16 08:00",
    "temp": 10.4,
    "desc": "kraftigt regn"
  },
  {
    "time": "2025-08-16 09:00",
    "temp": 9.9,
    "desc": null
  },
  {
    "time": "2025-08-16 10:00",
    "temp": 10.3,
    "desc": "kraftigt regn"
  },
  {
    "time": "2025-08-16 11:00",
    "temp": 10.4,
    "desc": "kraftigt regn"
  },
  {
    "time": "2025-08-16 12:00",
    "temp": 10.7,
    "desc": null
  },
  {
    "time": "2025-08-16 13:00",
    "temp": 11.0,
    "desc": null
  },
  {
    "time": "2025-08-16 14:00",
    "temp": 11.1,
    "desc": "regn"
  },
  {
    "time": "2025-08-16 15:00",
    "temp": 11.3,
    "desc": null
  },
  {
    "time": "2025-08-16 16:00",
    "temp": 11.2,
    "desc": null
  },
  {
    "time": "2025-08-16 17:00",
    "temp": 11.1,
    "desc": null
  },
  {
    "time": "2025-08-16 18:00",
    "temp": 11.1,
    "desc": null
  },
  {
    "time": "2025-08-16 19:00",
    "temp": 11.3,
    "desc": null
  },
  {
    "time": "2025-08-16 20:00",
    "temp": 11.3,
    "desc": null
  },
  {
    "time": "2025-08-16 21:00",
    "temp": 11.2,
    "desc": null
  },
  {
    "time": "2025-08-17 00:00",
    "temp": 10.8,
    "desc": null
  },
  {
    "time": "2025-08-17 06:00",
    "temp": 12.6,
    "desc": "regn"
  },
  {
    "time": "2025-08-17 12:00",
    "temp": 18.1,
    "desc": "lätt molnighet"
  },
  {
    "time": "2025-08-17 18:00",
    "temp": 14.4,
    "desc": "halvklart"
  },
  {
    "time": "2025-08-18 00:00",
    "temp": 10.2,
    "desc": "klart"
  },
  {
    "time": "2025-08-18 06:00",
    "temp": 14.1,
    "desc": "halvklart"
  },
  {
    "time": "2025-08-18 12:00",
    "temp": 20.7,
    "desc": "halvklart"
  },
  {
    "time": "2025-08-18 18:00",
    "temp": 16.7,
    "desc": "klart"
  },
  {
    "time": "2025-08-19 00:00",
    "temp": 13.1,
    "desc": "lätt molnighet"
  },
  {
    "time": "2025-08-19 06:00",
    "temp": 12.4,
    "desc": "halvklart"
  },
  {
    "time": "2025-08-19 12:00",
    "temp": 16.3,
    "desc": "halvklart"
  },
  {
    "time": "2025-08-19 18:00",
    "temp": 13.0,
    "desc": "klart"
  },
  {
    "time": "2025-08-20 00:00",
    "temp": 9.1,
    "desc": "klart"
  },
  {
    "time": "2025-08-20 06:00",
    "temp": 9.9,
    "desc": "lätt molnighet"
  },
  {
    "time": "2025-08-20 12:00",
    "temp": 15.7,
    "desc": "lätt molnighet"
  },
  {
    "time": "2025-08-21 00:00",
    "temp": 6.6,
    "desc": "klart"
  },
  {
    "time": "2025-08-21 12:00",
    "temp": 13.9,
    "desc": "lätt molnighet"
  },
  {
    "time": "2025-08-22 00:00",
    "temp": 7.8,
    "desc": "regn"
  },
  {
    "time": "2025-08-22 12:00",
    "temp": 13.1,
    "desc": "molnigt"
  },
  {
    "time": "2025-08-23 00:00",
    "temp": 8.5,
    "desc": "halvklart"
  },
  {
    "time": "2025-08-23 12:00",
    "temp": 13.1,
    "desc": "molnigt"
  },
  {
    "time": "2025-08-24 00:00",
    "temp": 9.1,
    "desc": "halvklart"
  }
]