{
  "cod": "200",
  "message": 0,
  "cnt": 40,
  "list": [
    {
      "dt": 1755961200,
      "main": {
        "temp": 15.72,
        "feels_like": 14.86,
        "temp_min": 15.72,
        "temp_max": 16.35,
        "pressure": 1007,
        "sea_level": 1007,
        "grnd_level": 1003,
        "humidity": 58,
        "temp_kf": -0.63
      },
      "weather": [
        {
          "id": 802,
          "main": "Clouds",
          "description": "växlande molnighet",
          "icon": "03d"
        }
      ],
      "clouds": {
        "all": 35
      },
      "wind": {
        "speed": 6.07,
        "deg": 338,
        "gust": 7.93
      },
      "visibility": 10000,
      "pop": 0,
      "sys": {
        "pod": "d"
      },
      "dt_txt": "2025-08-23 15:00:00"
    },
    {
      "dt": 1755972000,
      "main": {
        "temp": 14.06,
        "feels_like": 13.24,
        "temp_min": 13.38,
        "temp_max": 14.06,
        "pressure": 1008,
        "sea_level": 1008,
        "grnd_level": 1003,
        "humidity": 66,
        "temp_kf": 0.68
      },
      "weather": [
        {
          "id": 803,
          "main": "Clouds",
          "description": "molnigt",
          "icon": "04d"
        }
      ],
      "clouds": {
        "all": 61
      },
      "wind": {
        "speed": 3.03,
        "deg": 304,
        "gust": 8.99
      },
      "visibility": 10000,
      "pop": 0,
      "sys": {
        "pod": "d"
      },
      "dt_txt": "2025-08-23 18:00:00"
    },
    {
      "dt": 1755982800,
      "main": {
        "temp": 12.02,
        "feels_like": 10.92,
        "temp_min": 12.02,
        "temp_max": 12.02,
        "pressure": 1008,
        "sea_level": 1008,
        "grnd_level": 1003,
        "humidity": 63,
        "temp_kf": 0
      },
      "weather": [
        {
          "id": 804,
          "main": "Clouds",
          "description": "mulet",
          "icon": "04n"
        }
      ],
      "clouds": {
        "all": 100
      },
      "wind": {
        "speed": 4.52,
        "deg": 313,
        "gust": 10.2
      },
      "visibility": 10000,
      "pop": 0,
      "sys": {
        "pod": "n"
      },
      "dt_txt": "2025-08-23 21:00:00"
    },
    {
      "dt": 1755993600,
      "main": {
        "temp": 9.73,
        "feels_like": 7.43,
        "temp_min": 9.73,
        "temp_max": 9.73,
        "pressure": 1008,
        "sea_level": 1008,
        "grnd_level": 1003,
        "humidity": 62,
        "temp_kf": 0
      },
      "weather": [
        {
          "id": 804,
          "main": "Clouds",
          "description": "mulet",
          "icon": "04n"
        }
      ],
      "clouds": {
        "all": 97
      },
      "wind": {
        "speed": 4.55,
        "deg": 309,
        "gust": 10.58
      },
      "visibility": 10000,
      "pop": 0,
      "sys": {
        "pod": "n"
      },
      "dt_txt": "2025-08-24 00:00:00"
    },
    {
      "dt": 1756004400,
      "main": {
        "temp": 10.28,
        "feels_like": 9.06,
        "temp_min": 10.28,
        "temp_max": 10.28,
        "pressure": 1008,
        "sea_level": 1008,
        "grnd_level": 1003,
        "humidity": 65,
        "temp_kf": 0
      },
      "weather": [
        {
          "id": 803,
          "main": "Clouds",
          "description": "molnigt",
          "icon": "04n"
        }
      ],
      "clouds": {
        "all": 82
      },
      "wind": {
        "speed": 4.9,
        "deg": 307,
        "gust": 12.17
      },
      "visibility": 10000,
      "pop": 0,
      "sys": {
        "pod": "n"
      },
      "dt_txt": "2025-08-24 03:00:00"
    },
    {
      "dt": 1756015200,
      "main": {
        "temp": 11.27,
        "feels_like": 10.15,
        "temp_min": 11.27,
        "temp_max": 11.27,
        "pressure": 1008,
        "sea_level": 1008,
        "grnd_level": 1003,
        "humidity": 65,
        "temp_kf": 0
      },
      "weather": [
        {
          "id": 804,
          "main": "Clouds",
          "description": "mulet",
          "icon": "04d"
        }
      ],
      "clouds": {
        "all": 87
      },
      "wind": {
        "speed": 4.93,
        "deg": 311,
        "gust": 10.97
      },
      "visibility": 10000,
      "pop": 0,
      "sys": {
        "pod": "d"
      },
      "dt_txt": "2025-08-24 06:00:00"
    },
    {
      "dt": 1756026000,
      "main": {
        "temp": 13.8,
        "feels_like": 12.8,
        "temp_min": 13.8,
        "temp_max": 13.8,
        "pressure": 1008,
        "sea_level": 1008,
        "grnd_level": 1003,
        "humidity": 60,
        "temp_kf": 0
      },
      "weather": [
        {
          "id": 804,
          "main": "Clouds",
          "description": "mulet",
          "icon": "04d"
        }
      ],
      "clouds": {
        "all": 100
      },
      "wind": {
        "speed": 5.92,
        "deg": 323,
        "gust": 10.11
      },
      "visibility": 10000,
      "pop": 0,
      "sys": {
        "pod": "d"
      },
      "dt_txt": "2025-08-24 09:00:00"
    },
    {
      "dt": 1756036800,
      "main": {
        "temp": 15.35,
        "feels_like": 14.32,
        "temp_min": 15.35,
        "temp_max": 15.35,
        "pressure": 1008,
        "sea_level": 1008,
        "grnd_level": 1003,
        "humidity": 53,
        "temp_kf": 0
      },
      "weather": [
        {
          "id": 804,
          "main": "Clouds",
          "description": "mulet",
          "icon": "04d"
        }
      ],
      "clouds": {
        "all": 99
      },
      "wind": {
        "speed": 5.39,
        "deg": 327,
        "gust": 8.97
      },
      "visibility": 10000,
      "pop": 0,
      "sys": {
        "pod": "d"
      },
      "dt_txt": "2025-08-24 12:00:00"
    },
    {
      "dt": 1756047600,
      "main": {
        "temp": 15.47,
        "feels_like": 14.4,
        "temp_min": 15.47,
        "temp_max": 15.47,
        "pressure": 1008,
        "sea_level": 1008,
        "grnd_level": 1004,
        "humidity": 51,
        "temp_kf": 0
      },
      "weather": [
        {
          "id": 804,
          "main": "Clouds",
          "description": "mulet",
          "icon": "04d"
        }
      ],
      "clouds": {
        "all": 98
      },
      "wind": {
        "speed": 4.68,
        "deg": 318,
        "gust": 8.65
      },
      "visibility": 10000,
      "pop": 0,
      "sys": {
        "pod": "d"
      },
      "dt_txt": "2025-08-24 15:00:00"
    },
    {
      "dt": 1756058400,
      "main": {
        "temp": 14.04,
        "feels_like": 12.86,
        "temp_min": 14.04,
        "temp_max": 14.04,
        "pressure": 1008,
        "sea_level": 1008,
        "grnd_level": 1004,
        "humidity": 52,
        "temp_kf": 0
      },
      "weather": [
        {
          "id": 804,
          "main": "Clouds",
          "description": "mulet",
          "icon": "04d"
        }
      ],
      "clouds": {
        "all": 89
      },
      "wind": {
        "speed": 4.39,
        "deg": 315,
        "gust": 9.85
      },
      "visibility": 10000,
      "pop": 0,
      "sys": {
        "pod": "d"
      },
      "dt_txt": "2025-08-24 18:00:00"
    },
    {
      "dt": 1756069200,
      "main": {
        "temp": 10.75,
        "feels_like": 9.6,
        "temp_min": 10.75,
        "temp_max": 10.75,
        "pressure": 1009,
        "sea_level": 1009,
        "grnd_level": 1004,
        "humidity": 66,
        "temp_kf": 0
      },
      "weather": [
        {
          "id": 804,
          "main": "Clouds",
          "description": "mulet",
          "icon": "04n"
        }
      ],
      "clouds": {
        "all": 87
      },
      "wind": {
        "speed": 3.57,
        "deg": 320,
        "gust": 10.49
      },
      "visibility": 10000,
      "pop": 0,
      "sys": {
        "pod": "n"
      },
      "dt_txt": "2025-08-24 21:00:00"
    },
    {
      "dt": 1756080000,
      "main": {
        "temp": 9.37,
        "feels_like": 7.38,
        "temp_min": 9.37,
        "temp_max": 9.37,
        "pressure": 1009,
        "sea_level": 1009,
        "grnd_level": 1004,
        "humidity": 73,
        "temp_kf": 0
      },
      "weather": [
        {
          "id": 803,
          "main": "Clouds",
          "description": "molnigt",
          "icon": "04n"
        }
      ],
      "clouds": {
        "all": 80
      },
      "wind": {
        "speed": 3.68,
        "deg": 315,
        "gust": 10.85
      },
      "visibility": 10000,
      "pop": 0,
      "sys": {
        "pod": "n"
      },
      "dt_txt": "2025-08-25 00:00:00"
    },
    {
      "dt": 1756090800,
      "main": {
        "temp": 9.25,
        "feels_like": 7.13,
        "temp_min": 9.25,
        "temp_max": 9.25,
        "pressure": 1010,
        "sea_level": 1010,
        "grnd_level": 1005,
        "humidity": 76,
        "temp_kf": 0
      },
      "weather": [
        {
          "id": 804,
          "main": "Clouds",
          "description": "mulet",
          "icon": "04n"
        }
      ],
      "clouds": {
        "all": 100
      },
      "wind": {
        "speed": 3.9,
        "deg": 317,
        "gust": 11.27
      },
      "visibility": 10000,
      "pop": 0,
      "sys": {
        "pod": "n"
      },
      "dt_txt": "2025-08-25 03:00:00"
    },
    {
      "dt": 1756101600,
      "main": {
        "temp": 11.69,
        "feels_like": 10.61,
        "temp_min": 11.69,
        "temp_max": 11.69,
        "pressure": 1010,
        "sea_level": 1010,
        "grnd_level": 1005,
        "humidity": 65,
        "temp_kf": 0
      },
      "weather": [
        {
          "id": 803,
          "main": "Clouds",
          "description": "molnigt",
          "icon": "04d"
        }
      ],
      "clouds": {
        "all": 71
      },
      "wind": {
        "speed": 4.41,
        "deg": 327,
        "gust": 10.39
      },
      "visibility": 10000,
      "pop": 0,
      "sys": {
        "pod": "d"
      },
      "dt_txt": "2025-08-25 06:00:00"
    },
    {
      "dt": 1756112400,
      "main": {
        "temp": 15.94,
        "feels_like": 14.79,
        "temp_min": 15.94,
        "temp_max": 15.94,
        "pressure": 1010,
        "sea_level": 1010,
        "grnd_level": 1005,
        "humidity": 46,
        "temp_kf": 0
      },
      "weather": [
        {
          "id": 803,
          "main": "Clouds",
          "description": "molnigt",
          "icon": "04d"
        }
      ],
      "clouds": {
        "all": 76
      },
      "wind": {
        "speed": 5.04,
        "deg": 343,
        "gust": 7.78
      },
      "visibility": 10000,
      "pop": 0,
      "sys": {
        "pod": "d"
      },
      "dt_txt": "2025-08-25 09:00:00"
    },
    {
      "dt": 1756123200,
      "main": {
        "temp": 15.12,
        "feels_like": 13.94,
        "temp_min": 15.12,
        "temp_max": 15.12,
        "pressure": 1010,
        "sea_level": 1010,
        "grnd_level": 1005,
        "humidity": 48,
        "temp_kf": 0
      },
      "weather": [
        {
          "id": 803,
          "main": "Clouds",
          "description": "molnigt",
          "icon": "04d"
        }
      ],
      "clouds": {
        "all": 72
      },
      "wind": {
        "speed": 3.31,
        "deg": 348,
        "gust": 7.77
      },
      "visibility": 10000,
      "pop": 0,
      "sys": {
        "pod": "d"
      },
      "dt_txt": "2025-08-25 12:00:00"
    },
    {
      "dt": 1756134000,
      "main": {
        "temp": 16.63,
        "feels_like": 15.58,
        "temp_min": 16.63,
        "temp_max": 16.63,
        "pressure": 1011,
        "sea_level": 1011,
        "grnd_level": 1006,
        "humidity": 47,
        "temp_kf": 0
      },
      "weather": [
        {
          "id": 803,
          "main": "Clouds",
          "description": "molnigt",
          "icon": "04d"
        }
      ],
      "clouds": {
        "all": 84
      },
      "wind": {
        "speed": 4.31,
        "deg": 6,
        "gust": 6.95
      },
      "visibility": 10000,
      "pop": 0,
      "sys": {
        "pod": "d"
      },
      "dt_txt": "2025-08-25 15:00:00"
    },
    {
      "dt": 1756144800,
      "main": {
        "temp": 11.83,
        "feels_like": 10.95,
        "temp_min": 11.83,
        "temp_max": 11.83,
        "pressure": 1012,
        "sea_level": 1012,
        "grnd_level": 1007,
        "humidity": 72,
        "temp_kf": 0
      },
      "weather": [
        {
          "id": 500,
          "main": "Rain",
          "description": "lätt regn",
          "icon": "10d"
        }
      ],
      "clouds": {
        "all": 75
      },
      "wind": {
        "speed": 1.78,
        "deg": 335,
        "gust": 1.76
      },
      "visibility": 10000,
      "pop": 0.2,
      "rain": {
        "3h": 0.11
      },
      "sys": {
        "pod": "d"
      },
      "dt_txt": "2025-08-25 18:00:00"
    },
    {
      "dt": 1756155600,
      "main": {
        "temp": 10.07,
        "feels_like": 9.12,
        "temp_min": 10.07,
        "temp_max": 10.07,
        "pressure": 1012,
        "sea_level": 1012,
        "grnd_level": 1007,
        "humidity": 76,
        "temp_kf": 0
      },
      "weather": [
        {
          "id": 802,
          "main": "Clouds",
          "description": "växlande molnighet",
          "icon": "03n"
        }
      ],
      "clouds": {
        "all": 43
      },
      "wind": {
        "speed": 1.54,
        "deg": 327,
        "gust": 1.49
      },
      "visibility": 10000,
      "pop": 0,
      "sys": {
        "pod": "n"
      },
      "dt_txt": "2025-08-25 21:00:00"
    },
    {
      "dt": 1756166400,
      "main": {
        "temp": 9.42,
        "feels_like": 8.64,
        "temp_min": 9.42,
        "temp_max": 9.42,
        "pressure": 1012,
        "sea_level": 1012,
        "grnd_level": 1007,
        "humidity": 78,
        "temp_kf": 0
      },
      "weather": [
        {
          "id": 803,
          "main": "Clouds",
          "description": "molnigt",
          "icon": "04n"
        }
      ],
      "clouds": {
        "all": 57
      },
      "wind": {
        "speed": 1.86,
        "deg": 322,
        "gust": 2.2
      },
      "visibility": 10000,
      "pop": 0,
      "sys": {
        "pod": "n"
      },
      "dt_txt": "2025-08-26 00:00:00"
    },
    {
      "dt": 1756177200,
      "main": {
        "temp": 10.66,
        "feels_like": 9.56,
        "temp_min": 10.66,
        "temp_max": 10.66,
        "pressure": 1012,
        "sea_level": 1012,
        "grnd_level": 1007,
        "humidity": 68,
        "temp_kf": 0
      },
      "weather": [
        {
          "id": 804,
          "main": "Clouds",
          "description": "mulet",
          "icon": "04n"
        }
      ],
      "clouds": {
        "all": 100
      },
      "wind": {
        "speed": 1.99,
        "deg": 294,
        "gust": 4.08
      },
      "visibility": 10000,
      "pop": 0,
      "sys": {
        "pod": "n"
      },
      "dt_txt": "2025-08-26 03:00:00"
    },
    {
      "dt": 1756188000,
      "main": {
        "temp": 12.45,
        "feels_like": 11.29,
        "temp_min": 12.45,
        "temp_max": 12.45,
        "pressure": 1012,
        "sea_level": 1012,
        "grnd_level": 1007,
        "humidity": 59,
        "temp_kf": 0
      },
      "weather": [
        {
          "id": 804,
          "main": "Clouds",
          "description": "mulet",
          "icon": "04d"
        }
      ],
      "clouds": {
        "all": 100
      },
      "wind": {
        "speed": 1.65,
        "deg": 301,
        "gust": 3.01
      },
      "visibility": 10000,
      "pop": 0,
      "sys": {
        "pod": "d"
      },
      "dt_txt": "2025-08-26 06:00:00"
    },
    {
      "dt": 1756198800,
      "main": {
        "temp": 16.68,
        "feels_like": 15.42,
        "temp_min": 16.68,
        "temp_max": 16.68,
        "pressure": 1012,
        "sea_level": 1012,
        "grnd_level": 1007,
        "humidity": 39,
        "temp_kf": 0
      },
      "weather": [
        {
          "id": 804,
          "main": "Clouds",
          "description": "mulet",
          "icon": "04d"
        }
      ],
      "clouds": {
        "all": 96
      },
      "wind": {
        "speed": 2.19,
        "deg": 312,
        "gust": 4.17
      },
      "visibility": 10000,
      "pop": 0,
      "sys": {
        "pod": "d"
      },
      "dt_txt": "2025-08-26 09:00:00"
    },
    {
      "dt": 1756209600,
      "main": {
        "temp": 17.39,
        "feels_like": 16.12,
        "temp_min": 17.39,
        "temp_max": 17.39,
        "pressure": 1011,
        "sea_level": 1011,
        "grnd_level": 1006,
        "humidity": 36,
        "temp_kf": 0
      },
      "weather": [
        {
          "id": 804,
          "main": "Clouds",
          "description": "mulet",
          "icon": "04d"
        }
      ],
      "clouds": {
        "all": 96
      },
      "wind": {
        "speed": 1.67,
        "deg": 290,
        "gust": 3.15
      },
      "visibility": 10000,
      "pop": 0,
      "sys": {
        "pod": "d"
      },
      "dt_txt": "2025-08-26 12:00:00"
    },
    {
      "dt": 1756220400,
      "main": {
        "temp": 17.39,
        "feels_like": 16.2,
        "temp_min": 17.39,
        "temp_max": 17.39,
        "pressure": 1012,
        "sea_level": 1012,
        "grnd_level": 1007,
        "humidity": 39,
        "temp_kf": 0
      },
      "weather": [
        {
          "id": 804,
          "main": "Clouds",
          "description": "mulet",
          "icon": "04d"
        }
      ],
      "clouds": {
        "all": 100
      },
      "wind": {
        "speed": 1.19,
        "deg": 235,
        "gust": 2.01
      },
      "visibility": 10000,
      "pop": 0,
      "sys": {
        "pod": "d"
      },
      "dt_txt": "2025-08-26 15:00:00"
    },
    {
      "dt": 1756231200,
      "main": {
        "temp": 13.53,
        "feels_like": 12.51,
        "temp_min": 13.53,
        "temp_max": 13.53,
        "pressure": 1012,
        "sea_level": 1012,
        "grnd_level": 1007,
        "humidity": 60,
        "temp_kf": 0
      },
      "weather": [
        {
          "id": 804,
          "main": "Clouds",
          "description": "mulet",
          "icon": "04d"
        }
      ],
      "clouds": {
        "all": 100
      },
      "wind": {
        "speed": 1.51,
        "deg": 225,
        "gust": 2
      },
      "visibility": 10000,
      "pop": 0,
      "sys": {
        "pod": "d"
      },
      "dt_txt": "2025-08-26 18:00:00"
    },
    {
      "dt": 1756242000,
      "main": {
        "temp": 11.49,
        "feels_like": 10.42,
        "temp_min": 11.49,
        "temp_max": 11.49,
        "pressure": 1013,
        "sea_level": 1013,
        "grnd_level": 1008,
        "humidity": 66,
        "temp_kf": 0
      },
      "weather": [
        {
          "id": 804,
          "main": "Clouds",
          "description": "mulet",
          "icon": "04n"
        }
      ],
      "clouds": {
        "all": 100
      },
      "wind": {
        "speed": 1.42,
        "deg": 218,
        "gust": 1.5
      },
      "visibility": 10000,
      "pop": 0,
      "sys": {
        "pod": "n"
      },
      "dt_txt": "2025-08-26 21:00:00"
    },
    {
      "dt": 1756252800,
      "main": {
        "temp": 12.32,
        "feels_like": 11.33,
        "temp_min": 12.32,
        "temp_max": 12.32,
        "pressure": 1013,
        "sea_level": 1013,
        "grnd_level": 1008,
        "humidity": 66,
        "temp_kf": 0
      },
      "weather": [
        {
          "id": 804,
          "main": "Clouds",
          "description": "mulet",
          "icon": "04n"
        }
      ],
      "clouds": {
        "all": 100
      },
      "wind": {
        "speed": 1.74,
        "deg": 212,
        "gust": 2.86
      },
      "visibility": 10000,
      "pop": 0,
      "sys": {
        "pod": "n"
      },
      "dt_txt": "2025-08-27 00:00:00"
    },
    {
      "dt": 1756263600,
      "main": {
        "temp": 12.37,
        "feels_like": 11.39,
        "temp_min": 12.37,
        "temp_max": 12.37,
        "pressure": 1012,
        "sea_level": 1012,
        "grnd_level": 1007,
        "humidity": 66,
        "temp_kf": 0
      },
      "weather": [
        {
          "id": 804,
          "main": "Clouds",
          "description": "mulet",
          "icon": "04n"
        }
      ],
      "clouds": {
        "all": 100
      },
      "wind": {
        "speed": 1.76,
        "deg": 190,
        "gust": 2.51
      },
      "visibility": 10000,
      "pop": 0,
      "sys": {
        "pod": "n"
      },
      "dt_txt": "2025-08-27 03:00:00"
    },
    {
      "dt": 1756274400,
      "main": {
        "temp": 13.52,
        "feels_like": 12.6,
        "temp_min": 13.52,
        "temp_max": 13.52,
        "pressure": 1013,
        "sea_level": 1013,
        "grnd_level": 1008,
        "humidity": 64,
        "temp_kf": 0
      },
      "weather": [
        {
          "id": 804,
          "main": "Clouds",
          "description": "mulet",
          "icon": "04d"
        }
      ],
      "clouds": {
        "all": 100
      },
      "wind": {
        "speed": 1.71,
        "deg": 162,
        "gust": 3.48
      },
      "visibility": 10000,
      "pop": 0,
      "sys": {
        "pod": "d"
      },
      "dt_txt": "2025-08-27 06:00:00"
    },
    {
      "dt": 1756285200,
      "main": {
        "temp": 16.99,
        "feels_like": 16.13,
        "temp_min": 16.99,
        "temp_max": 16.99,
        "pressure": 1013,
        "sea_level": 1013,
        "grnd_level": 1008,
        "humidity": 53,
        "temp_kf": 0
      },
      "weather": [
        {
          "id": 804,
          "main": "Clouds",
          "description": "mulet",
          "icon": "04d"
        }
      ],
      "clouds": {
        "all": 100
      },
      "wind": {
        "speed": 2.19,
        "deg": 235,
        "gust": 3.11
      },
      "visibility": 10000,
      "pop": 0,
      "sys": {
        "pod": "d"
      },
      "dt_txt": "2025-08-27 09:00:00"
    },
    {
      "dt": 1756296000,
      "main": {
        "temp": 15.95,
        "feels_like": 15.25,
        "temp_min": 15.95,
        "temp_max": 15.95,
        "pressure": 1013,
        "sea_level": 1013,
        "grnd_level": 1008,
        "humidity": 63,
        "temp_kf": 0
      },
      "weather": [
        {
          "id": 804,
          "main": "Clouds",
          "description": "mulet",
          "icon": "04d"
        }
      ],
      "clouds": {
        "all": 100
      },
      "wind": {
        "speed": 1.06,
        "deg": 247,
        "gust": 2.1
      },
      "visibility": 10000,
      "pop": 0,
      "sys": {
        "pod": "d"
      },
      "dt_txt": "2025-08-27 12:00:00"
    },
    {
      "dt": 1756306800,
      "main": {
        "temp": 16.43,
        "feels_like": 15.64,
        "temp_min": 16.43,
        "temp_max": 16.43,
        "pressure": 1012,
        "sea_level": 1012,
        "grnd_level": 1007,
        "humidity": 58,
        "temp_kf": 0
      },
      "weather": [
        {
          "id": 804,
          "main": "Clouds",
          "description": "mulet",
          "icon": "04d"
        }
      ],
      "clouds": {
        "all": 100
      },
      "wind": {
        "speed": 2.23,
        "deg": 155,
        "gust": 3.83
      },
      "visibility": 10000,
      "pop": 0,
      "sys": {
        "pod": "d"
      },
      "dt_txt": "2025-08-27 15:00:00"
    },
    {
      "dt": 1756317600,
      "main": {
        "temp": 14.26,
        "feels_like": 13.46,
        "temp_min": 14.26,
        "temp_max": 14.26,
        "pressure": 1012,
        "sea_level": 1012,
        "grnd_level": 1007,
        "humidity": 66,
        "temp_kf": 0
      },
      "weather": [
        {
          "id": 804,
          "main": "Clouds",
          "description": "mulet",
          "icon": "04d"
        }
      ],
      "clouds": {
        "all": 100
      },
      "wind": {
        "speed": 1.58,
        "deg": 142,
        "gust": 1.4
      },
      "visibility": 10000,
      "pop": 0,
      "sys": {
        "pod": "d"
      },
      "dt_txt": "2025-08-27 18:00:00"
    },
    {
      "dt": 1756328400,
      "main": {
        "temp": 13.75,
        "feels_like": 13.43,
        "temp_min": 13.75,
        "temp_max": 13.75,
        "pressure": 1012,
        "sea_level": 1012,
        "grnd_level": 1007,
        "humidity": 86,
        "temp_kf": 0
      },
      "weather": [
        {
          "id": 804,
          "main": "Clouds",
          "description": "mulet",
          "icon": "04n"
        }
      ],
      "clouds": {
        "all": 100
      },
      "wind": {
        "speed": 1.79,
        "deg": 110,
        "gust": 2.93
      },
      "visibility": 10000,
      "pop": 0,
      "sys": {
        "pod": "n"
      },
      "dt_txt": "2025-08-27 21:00:00"
    },
    {
      "dt": 1756339200,
      "main": {
        "temp": 12.77,
        "feels_like": 12.61,
        "temp_min": 12.77,
        "temp_max": 12.77,
        "pressure": 1012,
        "sea_level": 1012,
        "grnd_level": 1007,
        "humidity": 96,
        "temp_kf": 0
      },
      "weather": [
        {
          "id": 804,
          "main": "Clouds",
          "description": "mulet",
          "icon": "04n"
        }
      ],
      "clouds": {
        "all": 91
      },
      "wind": {
        "speed": 2.08,
        "deg": 117,
        "gust": 4.96
      },
      "visibility": 10000,
      "pop": 0,
      "sys": {
        "pod": "n"
      },
      "dt_txt": "2025-08-28 00:00:00"
    },
    {
      "dt": 1756350000,
      "main": {
        "temp": 12.16,
        "feels_like": 11.96,
        "temp_min": 12.16,
        "temp_max": 12.16,
        "pressure": 1011,
        "sea_level": 1011,
        "grnd_level": 1006,
        "humidity": 97,
        "temp_kf": 0
      },
      "weather": [
        {
          "id": 803,
          "main": "Clouds",
          "description": "molnigt",
          "icon": "04n"
        }
      ],
      "clouds": {
        "all": 77
      },
      "wind": {
        "speed": 2.38,
        "deg": 105,
        "gust": 7.64
      },
      "visibility": 10000,
      "pop": 0,
      "sys": {
        "pod": "n"
      },
      "dt_txt": "2025-08-28 03:00:00"
    },
    {
      "dt": 1756360800,
      "main": {
        "temp": 14.71,
        "feels_like": 14.38,
        "temp_min": 14.71,
        "temp_max": 14.71,
        "pressure": 1010,
        "sea_level": 1010,
        "grnd_level": 1005,
        "humidity": 82,
        "temp_kf": 0
      },
      "weather": [
        {
          "id": 804,
          "main": "Clouds",
          "description": "mulet",
          "icon": "04d"
        }
      ],
      "clouds": {
        "all": 89
      },
      "wind": {
        "speed": 3.59,
        "deg": 99,
        "gust": 10.43
      },
      "visibility": 10000,
      "pop": 0,
      "sys": {
        "pod": "d"
      },
      "dt_txt": "2025-08-28 06:00:00"
    },
    {
      "dt": 1756371600,
      "main": {
        "temp": 18.42,
        "feels_like": 18.09,
        "temp_min": 18.42,
        "temp_max": 18.42,
        "pressure": 1009,
        "sea_level": 1009,
        "grnd_level": 1004,
        "humidity": 68,
        "temp_kf": 0
      },
      "weather": [
        {
          "id": 804,
          "main": "Clouds",
          "description": "mulet",
          "icon": "04d"
        }
      ],
      "clouds": {
        "all": 100
      },
      "wind": {
        "speed": 5,
        "deg": 98,
        "gust": 10.59
      },
      "visibility": 10000,
      "pop": 0,
      "sys": {
        "pod": "d"
      },
      "dt_txt": "2025-08-28 09:00:00"
    },
    {
      "dt": 1756382400,
      "main": {
        "temp": 20.7,
        "feels_like": 20.29,
        "temp_min": 20.7,
        "temp_max": 20.7,
        "pressure": 1008,
        "sea_level": 1008,
        "grnd_level": 1003,
        "humidity": 56,
        "temp_kf": 0
      },
      "weather": [
        {
          "id": 804,
          "main": "Clouds",
          "description": "mulet",
          "icon": "04d"
        }
      ],
      "clouds": {
        "all": 100
      },
      "wind": {
        "speed": 5.61,
        "deg": 132,
        "gust": 9.16
      },
      "visibility": 10000,
      "pop": 0,
      "sys": {
        "pod": "d"
      },
      "dt_txt": "2025-08-28 12:00:00"
    }
  ],
  "city": {
    "id": 2715953,
    "name": "Eskilstuna",
    "coord": {
      "lat": 59.3666,
      "lon": 16.5077
    },
    "country": "SE",
    "population": 59016,
    "timezone": 7200,
    "sunrise": 1755919805,
    "sunset": 1755973412
  }
}