[
  {
    "time": "2025-10-21T18:00:00Z",
    "data": {
      "instant": {
        "details": {
          "air_pressure_at_sea_level": 992.7,
          "air_temperature": 11.1,
          "cloud_area_fraction": 100.0,
          "relative_humidity": 90.2,
          "wind_from_direction": 131.9,
          "wind_speed": 6.1
        }
      },
      "next_12_hours": {
        "summary": {
          "symbol_code": "rain"
        },
        "details": {}
      },
      "next_1_hours": {
        "summary": {
          "symbol_code": "rain"
        },
        "details": {
          "precipitation_amount": 0.2
        }
      },
      "next_6_hours": {
        "summary": {
          "symbol_code": "rain"
        },
        "details": {
          "precipitation_amount": 3.2
        }
      }
    }
  },
  {
    "time": "2025-10-21T19:00:00Z",
    "data": {
      "instant": {
        "details": {
          "air_pressure_at_sea_level": 992.4,
          "air_temperature": 11.0,
          "cloud_area_fraction": 100.0,
          "relative_humidity": 90.7,
          "wind_from_direction": 133.7,
          "wind_speed": 6.5
        }
      },
      "next_12_hours": {
        "summary": {
          "symbol_code": "rain"
        },
        "details": {}
      },
      "next_1_hours": {
        "summary": {
          "symbol_code": "lightrain"
        },
        "details": {
          "precipitation_amount": 0.1
        }
      },
      "next_6_hours": {
        "summary": {
          "symbol_code": "rain"
        },
        "details": {
          "precipitation_amount": 3.4
        }
      }
    }
  },
  {
    "time": "2025-10-21T20:00:00Z",
    "data": {
      "instant": {
        "details": {
          "air_pressure_at_sea_level": 992.2,
          "air_temperature": 11.1,
          "cloud_area_fraction": 100.0,
          "relative_humidity": 92.2,
          "wind_from_direction": 135.1,
          "wind_speed": 6.1
        }
      },
      "next_12_hours": {
        "summary": {
          "symbol_code": "rain"
        },
        "details": {}
      },
      "next_1_hours": {
        "summary": {
          "symbol_code": "rain"
        },
        "details": {
          "precipitation_amount": 0.3
        }
      },
      "next_6_hours": {
        "summary": {
          "symbol_code": "rain"
        },
        "details": {
          "precipitation_amount": 3.8
        }
      }
    }
  }
]