{
  "cod": "200",
  "message": 0,
  "cnt": 40,
  "list": [
    {
      "dt": 1754838000,
      "main": {
        "temp": 18.11,
        "feels_like": 17.78,
        "temp_min": 18.11,
        "temp_max": 19.08,
        "pressure": 1020,
        "sea_level": 1020,
        "grnd_level": 1015,
        "humidity": 69,
        "temp_kf": -0.97
      },
      "weather": [
        {
          "id": 802,
          "main": "Clouds",
          "description": "växlande molnighet",
          "icon": "03d"
        }
      ],
      "clouds": {
        "all": 50
      },
      "wind": {
        "speed": 7.7,
        "deg": 271,
        "gust": 10.56
      },
      "visibility": 10000,
      "pop": 0,
      "sys": {
        "pod": "d"
      },
      "dt_txt": "2025-08-10 15:00:00"
    },
    {
      "dt": 1754848800,
      "main": {
        "temp": 17.62,
        "feels_like": 17.4,
        "temp_min": 17.62,
        "temp_max": 17.62,
        "pressure": 1021,
        "sea_level": 1021,
        "grnd_level": 1015,
        "humidity": 75,
        "temp_kf": 0
      },
      "weather": [
        {
          "id": 802,
          "main": "Clouds",
          "description": "växlande molnighet",
          "icon": "03d"
        }
      ],
      "clouds": {
        "all": 25
      },
      "wind": {
        "speed": 7.18,
        "deg": 270,
        "gust": 12.17
      },
      "visibility": 10000,
      "pop": 0,
      "sys": {
        "pod": "d"
      },
      "dt_txt": "2025-08-10 18:00:00"
    },
    {
      "dt": 1754859600,
      "main": {
        "temp": 17.36,
        "feels_like": 17.32,
        "temp_min": 17.36,
        "temp_max": 17.36,
        "pressure": 1022,
        "sea_level": 1022,
        "grnd_level": 1017,
        "humidity": 83,
        "temp_kf": 0
      },
      "weather": [
        {
          "id": 802,
          "main": "Clouds",
          "description": "växlande molnighet",
          "icon": "03n"
        }
      ],
      "clouds": {
        "all": 37
      },
      "wind": {
        "speed": 6.83,
        "deg": 269,
        "gust": 11.37
      },
      "visibility": 10000,
      "pop": 0,
      "sys": {
        "pod": "n"
      },
      "dt_txt": "2025-08-10 21:00:00"
    },
    {
      "dt": 1754870400,
      "main": {
        "temp": 16.13,
        "feels_like": 15.91,
        "temp_min": 16.13,
        "temp_max": 16.13,
        "pressure": 1022,
        "sea_level": 1022,
        "grnd_level": 1017,
        "humidity": 81,
        "temp_kf": 0
      },
      "weather": [
        {
          "id": 803,
          "main": "Clouds",
          "description": "molnigt",
          "icon": "04n"
        }
      ],
      "clouds": {
        "all": 64
      },
      "wind": {
        "speed": 5.65,
        "deg": 266,
        "gust": 8.9
      },
      "visibility": 10000,
      "pop": 0,
      "sys": {
        "pod": "n"
      },
      "dt_txt": "2025-08-11 00:00:00"
    },
    {
      "dt": 1754881200,
      "main": {
        "temp": 15.74,
        "feels_like": 15.43,
        "temp_min": 15.74,
        "temp_max": 15.74,
        "pressure": 1022,
        "sea_level": 1022,
        "grnd_level": 1016,
        "humidity": 79,
        "temp_kf": 0
      },
      "weather": [
        {
          "id": 804,
          "main": "Clouds",
          "description": "mulet",
          "icon": "04n"
        }
      ],
      "clouds": {
        "all": 100
      },
      "wind": {
        "speed": 5.46,
        "deg": 258,
        "gust": 8.74
      },
      "visibility": 10000,
      "pop": 0,
      "sys": {
        "pod": "n"
      },
      "dt_txt": "2025-08-11 03:00:00"
    },
    {
      "dt": 1754892000,
      "main": {
        "temp": 15.07,
        "feels_like": 14.56,
        "temp_min": 15.07,
        "temp_max": 15.07,
        "pressure": 1021,
        "sea_level": 1021,
        "grnd_level": 1016,
        "humidity": 74,
        "temp_kf": 0
      },
      "weather": [
        {
          "id": 804,
          "main": "Clouds",
          "description": "mulet",
          "icon": "04d"
        }
      ],
      "clouds": {
        "all": 100
      },
      "wind": {
        "speed": 6.07,
        "deg": 256,
        "gust": 8.84
      },
      "visibility": 10000,
      "pop": 0,
      "sys": {
        "pod": "d"
      },
      "dt_txt": "2025-08-11 06:00:00"
    },
    {
      "dt": 1754902800,
      "main": {
        "temp": 16.88,
        "feels_like": 16.32,
        "temp_min": 16.88,
        "temp_max": 16.88,
        "pressure": 1021,
        "sea_level": 1021,
        "grnd_level": 1016,
        "humidity": 65,
        "temp_kf": 0
      },
      "weather": [
        {
          "id": 804,
          "main": "Clouds",
          "description": "mulet",
          "icon": "04d"
        }
      ],
      "clouds": {
        "all": 100
      },
      "wind": {
        "speed": 6.03,
        "deg": 251,
        "gust": 7.81
      },
      "visibility": 10000,
      "pop": 0,
      "sys": {
        "pod": "d"
      },
      "dt_txt": "2025-08-11 09:00:00"
    },
    {
      "dt": 1754913600,
      "main": {
        "temp": 17.2,
        "feels_like": 16.62,
        "temp_min": 17.2,
        "temp_max": 17.2,
        "pressure": 1021,
        "sea_level": 1021,
        "grnd_level": 1016,
        "humidity": 63,
        "temp_kf": 0
      },
      "weather": [
        {
          "id": 804,
          "main": "Clouds",
          "description": "mulet",
          "icon": "04d"
        }
      ],
      "clouds": {
        "all": 95
      },
      "wind": {
        "speed": 5.89,
        "deg": 254,
        "gust": 7.81
      },
      "visibility": 10000,
      "pop": 0,
      "sys": {
        "pod": "d"
      },
      "dt_txt": "2025-08-11 12:00:00"
    },
    {
      "dt": 1754924400,
      "main": {
        "temp": 17.61,
        "feels_like": 17.25,
        "temp_min": 17.61,
        "temp_max": 17.61,
        "pressure": 1019,
        "sea_level": 1019,
        "grnd_level": 1014,
        "humidity": 70,
        "temp_kf": 0
      },
      "weather": [
        {
          "id": 500,
          "main": "Rain",
          "description": "lätt regn",
          "icon": "10d"
        }
      ],
      "clouds": {
        "all": 60
      },
      "wind": {
        "speed": 5.73,
        "deg": 249,
        "gust": 8.25
      },
      "visibility": 10000,
      "pop": 0.2,
      "rain": {
        "3h": 0.21
      },
      "sys": {
        "pod": "d"
      },
      "dt_txt": "2025-08-11 15:00:00"
    },
    {
      "dt": 1754935200,
      "main": {
        "temp": 16.38,
        "feels_like": 16.27,
        "temp_min": 16.38,
        "temp_max": 16.38,
        "pressure": 1018,
        "sea_level": 1018,
        "grnd_level": 1013,
        "humidity": 84,
        "temp_kf": 0
      },
      "weather": [
        {
          "id": 500,
          "main": "Rain",
          "description": "lätt regn",
          "icon": "10d"
        }
      ],
      "clouds": {
        "all": 67
      },
      "wind": {
        "speed": 5.67,
        "deg": 240,
        "gust": 9
      },
      "visibility": 10000,
      "pop": 0.47,
      "rain": {
        "3h": 0.43
      },
      "sys": {
        "pod": "d"
      },
      "dt_txt": "2025-08-11 18:00:00"
    },
    {
      "dt": 1754946000,
      "main": {
        "temp": 15.45,
        "feels_like": 15.35,
        "temp_min": 15.45,
        "temp_max": 15.45,
        "pressure": 1018,
        "sea_level": 1018,
        "grnd_level": 1013,
        "humidity": 88,
        "temp_kf": 0
      },
      "weather": [
        {
          "id": 500,
          "main": "Rain",
          "description": "lätt regn",
          "icon": "10n"
        }
      ],
      "clouds": {
        "all": 37
      },
      "wind": {
        "speed": 5.05,
        "deg": 260,
        "gust": 8.96
      },
      "visibility": 10000,
      "pop": 0.2,
      "rain": {
        "3h": 0.1
      },
      "sys": {
        "pod": "n"
      },
      "dt_txt": "2025-08-11 21:00:00"
    },
    {
      "dt": 1754956800,
      "main": {
        "temp": 16,
        "feels_like": 15.95,
        "temp_min": 16,
        "temp_max": 16,
        "pressure": 1018,
        "sea_level": 1018,
        "grnd_level": 1013,
        "humidity": 88,
        "temp_kf": 0
      },
      "weather": [
        {
          "id": 802,
          "main": "Clouds",
          "description": "växlande molnighet",
          "icon": "03n"
        }
      ],
      "clouds": {
        "all": 43
      },
      "wind": {
        "speed": 5.99,
        "deg": 264,
        "gust": 9.6
      },
      "visibility": 10000,
      "pop": 0,
      "sys": {
        "pod": "n"
      },
      "dt_txt": "2025-08-12 00:00:00"
    },
    {
      "dt": 1754967600,
      "main": {
        "temp": 16.19,
        "feels_like": 15.95,
        "temp_min": 16.19,
        "temp_max": 16.19,
        "pressure": 1018,
        "sea_level": 1018,
        "grnd_level": 1013,
        "humidity": 80,
        "temp_kf": 0
      },
      "weather": [
        {
          "id": 804,
          "main": "Clouds",
          "description": "mulet",
          "icon": "04n"
        }
      ],
      "clouds": {
        "all": 87
      },
      "wind": {
        "speed": 5.62,
        "deg": 271,
        "gust": 7.8
      },
      "visibility": 10000,
      "pop": 0,
      "sys": {
        "pod": "n"
      },
      "dt_txt": "2025-08-12 03:00:00"
    },
    {
      "dt": 1754978400,
      "main": {
        "temp": 16.67,
        "feels_like": 16.3,
        "temp_min": 16.67,
        "temp_max": 16.67,
        "pressure": 1018,
        "sea_level": 1018,
        "grnd_level": 1013,
        "humidity": 73,
        "temp_kf": 0
      },
      "weather": [
        {
          "id": 803,
          "main": "Clouds",
          "description": "molnigt",
          "icon": "04d"
        }
      ],
      "clouds": {
        "all": 80
      },
      "wind": {
        "speed": 4.93,
        "deg": 264,
        "gust": 6.53
      },
      "visibility": 10000,
      "pop": 0,
      "sys": {
        "pod": "d"
      },
      "dt_txt": "2025-08-12 06:00:00"
    },
    {
      "dt": 1754989200,
      "main": {
        "temp": 18.21,
        "feels_like": 17.71,
        "temp_min": 18.21,
        "temp_max": 18.21,
        "pressure": 1019,
        "sea_level": 1019,
        "grnd_level": 1014,
        "humidity": 62,
        "temp_kf": 0
      },
      "weather": [
        {
          "id": 801,
          "main": "Clouds",
          "description": "lätt molnighet",
          "icon": "02d"
        }
      ],
      "clouds": {
        "all": 20
      },
      "wind": {
        "speed": 4.64,
        "deg": 253,
        "gust": 5.39
      },
      "visibility": 10000,
      "pop": 0,
      "sys": {
        "pod": "d"
      },
      "dt_txt": "2025-08-12 09:00:00"
    },
    {
      "dt": 1755000000,
      "main": {
        "temp": 19.3,
        "feels_like": 18.67,
        "temp_min": 19.3,
        "temp_max": 19.3,
        "pressure": 1019,
        "sea_level": 1019,
        "grnd_level": 1014,
        "humidity": 53,
        "temp_kf": 0
      },
      "weather": [
        {
          "id": 801,
          "main": "Clouds",
          "description": "lätt molnighet",
          "icon": "02d"
        }
      ],
      "clouds": {
        "all": 11
      },
      "wind": {
        "speed": 3.8,
        "deg": 254,
        "gust": 5.14
      },
      "visibility": 10000,
      "pop": 0,
      "sys": {
        "pod": "d"
      },
      "dt_txt": "2025-08-12 12:00:00"
    },
    {
      "dt": 1755010800,
      "main": {
        "temp": 18.84,
        "feels_like": 18.19,
        "temp_min": 18.84,
        "temp_max": 18.84,
        "pressure": 1019,
        "sea_level": 1019,
        "grnd_level": 1014,
        "humidity": 54,
        "temp_kf": 0
      },
      "weather": [
        {
          "id": 803,
          "main": "Clouds",
          "description": "molnigt",
          "icon": "04d"
        }
      ],
      "clouds": {
        "all": 61
      },
      "wind": {
        "speed": 3.22,
        "deg": 249,
        "gust": 5.18
      },
      "visibility": 10000,
      "pop": 0,
      "sys": {
        "pod": "d"
      },
      "dt_txt": "2025-08-12 15:00:00"
    },
    {
      "dt": 1755021600,
      "main": {
        "temp": 16.21,
        "feels_like": 15.71,
        "temp_min": 16.21,
        "temp_max": 16.21,
        "pressure": 1019,
        "sea_level": 1019,
        "grnd_level": 1014,
        "humidity": 70,
        "temp_kf": 0
      },
      "weather": [
        {
          "id": 803,
          "main": "Clouds",
          "description": "molnigt",
          "icon": "04d"
        }
      ],
      "clouds": {
        "all": 80
      },
      "wind": {
        "speed": 1.92,
        "deg": 252,
        "gust": 3.34
      },
      "visibility": 10000,
      "pop": 0,
      "sys": {
        "pod": "d"
      },
      "dt_txt": "2025-08-12 18:00:00"
    },
    {
      "dt": 1755032400,
      "main": {
        "temp": 13.94,
        "feels_like": 13.45,
        "temp_min": 13.94,
        "temp_max": 13.94,
        "pressure": 1020,
        "sea_level": 1020,
        "grnd_level": 1015,
        "humidity": 79,
        "temp_kf": 0
      },
      "weather": [
        {
          "id": 804,
          "main": "Clouds",
          "description": "mulet",
          "icon": "04n"
        }
      ],
      "clouds": {
        "all": 98
      },
      "wind": {
        "speed": 0.92,
        "deg": 254,
        "gust": 1.33
      },
      "visibility": 10000,
      "pop": 0,
      "sys": {
        "pod": "n"
      },
      "dt_txt": "2025-08-12 21:00:00"
    },
    {
      "dt": 1755043200,
      "main": {
        "temp": 13.48,
        "feels_like": 13.08,
        "temp_min": 13.48,
        "temp_max": 13.48,
        "pressure": 1020,
        "sea_level": 1020,
        "grnd_level": 1015,
        "humidity": 84,
        "temp_kf": 0
      },
      "weather": [
        {
          "id": 803,
          "main": "Clouds",
          "description": "molnigt",
          "icon": "04n"
        }
      ],
      "clouds": {
        "all": 77
      },
      "wind": {
        "speed": 0.7,
        "deg": 171,
        "gust": 1.09
      },
      "visibility": 10000,
      "pop": 0,
      "sys": {
        "pod": "n"
      },
      "dt_txt": "2025-08-13 00:00:00"
    },
    {
      "dt": 1755054000,
      "main": {
        "temp": 13.31,
        "feels_like": 12.94,
        "temp_min": 13.31,
        "temp_max": 13.31,
        "pressure": 1020,
        "sea_level": 1020,
        "grnd_level": 1015,
        "humidity": 86,
        "temp_kf": 0
      },
      "weather": [
        {
          "id": 803,
          "main": "Clouds",
          "description": "molnigt",
          "icon": "04n"
        }
      ],
      "clouds": {
        "all": 80
      },
      "wind": {
        "speed": 1.72,
        "deg": 149,
        "gust": 1.78
      },
      "visibility": 10000,
      "pop": 0,
      "sys": {
        "pod": "n"
      },
      "dt_txt": "2025-08-13 03:00:00"
    },
    {
      "dt": 1755064800,
      "main": {
        "temp": 16.7,
        "feels_like": 16.28,
        "temp_min": 16.7,
        "temp_max": 16.7,
        "pressure": 1021,
        "sea_level": 1021,
        "grnd_level": 1015,
        "humidity": 71,
        "temp_kf": 0
      },
      "weather": [
        {
          "id": 804,
          "main": "Clouds",
          "description": "mulet",
          "icon": "04d"
        }
      ],
      "clouds": {
        "all": 87
      },
      "wind": {
        "speed": 1.57,
        "deg": 162,
        "gust": 2.29
      },
      "visibility": 10000,
      "pop": 0,
      "sys": {
        "pod": "d"
      },
      "dt_txt": "2025-08-13 06:00:00"
    },
    {
      "dt": 1755075600,
      "main": {
        "temp": 20.38,
        "feels_like": 19.99,
        "temp_min": 20.38,
        "temp_max": 20.38,
        "pressure": 1021,
        "sea_level": 1021,
        "grnd_level": 1016,
        "humidity": 58,
        "temp_kf": 0
      },
      "weather": [
        {
          "id": 804,
          "main": "Clouds",
          "description": "mulet",
          "icon": "04d"
        }
      ],
      "clouds": {
        "all": 99
      },
      "wind": {
        "speed": 2.05,
        "deg": 207,
        "gust": 1.93
      },
      "visibility": 10000,
      "pop": 0,
      "sys": {
        "pod": "d"
      },
      "dt_txt": "2025-08-13 09:00:00"
    },
    {
      "dt": 1755086400,
      "main": {
        "temp": 19.62,
        "feels_like": 19.33,
        "temp_min": 19.62,
        "temp_max": 19.62,
        "pressure": 1020,
        "sea_level": 1020,
        "grnd_level": 1015,
        "humidity": 65,
        "temp_kf": 0
      },
      "weather": [
        {
          "id": 500,
          "main": "Rain",
          "description": "lätt regn",
          "icon": "10d"
        }
      ],
      "clouds": {
        "all": 99
      },
      "wind": {
        "speed": 2.17,
        "deg": 194,
        "gust": 2.86
      },
      "visibility": 10000,
      "pop": 0.2,
      "rain": {
        "3h": 0.11
      },
      "sys": {
        "pod": "d"
      },
      "dt_txt": "2025-08-13 12:00:00"
    },
    {
      "dt": 1755097200,
      "main": {
        "temp": 22.84,
        "feels_like": 22.56,
        "temp_min": 22.84,
        "temp_max": 22.84,
        "pressure": 1020,
        "sea_level": 1020,
        "grnd_level": 1015,
        "humidity": 53,
        "temp_kf": 0
      },
      "weather": [
        {
          "id": 803,
          "main": "Clouds",
          "description": "molnigt",
          "icon": "04d"
        }
      ],
      "clouds": {
        "all": 84
      },
      "wind": {
        "speed": 1.96,
        "deg": 177,
        "gust": 3.4
      },
      "visibility": 10000,
      "pop": 0,
      "sys": {
        "pod": "d"
      },
      "dt_txt": "2025-08-13 15:00:00"
    },
    {
      "dt": 1755108000,
      "main": {
        "temp": 20.51,
        "feels_like": 20.34,
        "temp_min": 20.51,
        "temp_max": 20.51,
        "pressure": 1019,
        "sea_level": 1019,
        "grnd_level": 1014,
        "humidity": 66,
        "temp_kf": 0
      },
      "weather": [
        {
          "id": 803,
          "main": "Clouds",
          "description": "molnigt",
          "icon": "04d"
        }
      ],
      "clouds": {
        "all": 51
      },
      "wind": {
        "speed": 0.17,
        "deg": 225,
        "gust": 0.27
      },
      "visibility": 10000,
      "pop": 0,
      "sys": {
        "pod": "d"
      },
      "dt_txt": "2025-08-13 18:00:00"
    },
    {
      "dt": 1755118800,
      "main": {
        "temp": 17.39,
        "feels_like": 17.01,
        "temp_min": 17.39,
        "temp_max": 17.39,
        "pressure": 1020,
        "sea_level": 1020,
        "grnd_level": 1015,
        "humidity": 70,
        "temp_kf": 0
      },
      "weather": [
        {
          "id": 802,
          "main": "Clouds",
          "description": "växlande molnighet",
          "icon": "03n"
        }
      ],
      "clouds": {
        "all": 28
      },
      "wind": {
        "speed": 2.42,
        "deg": 107,
        "gust": 4.38
      },
      "visibility": 10000,
      "pop": 0,
      "sys": {
        "pod": "n"
      },
      "dt_txt": "2025-08-13 21:00:00"
    },
    {
      "dt": 1755129600,
      "main": {
        "temp": 15.83,
        "feels_like": 14.93,
        "temp_min": 15.83,
        "temp_max": 15.83,
        "pressure": 1020,
        "sea_level": 1020,
        "grnd_level": 1015,
        "humidity": 56,
        "temp_kf": 0
      },
      "weather": [
        {
          "id": 802,
          "main": "Clouds",
          "description": "växlande molnighet",
          "icon": "03n"
        }
      ],
      "clouds": {
        "all": 39
      },
      "wind": {
        "speed": 3.47,
        "deg": 121,
        "gust": 9.82
      },
      "visibility": 10000,
      "pop": 0,
      "sys": {
        "pod": "n"
      },
      "dt_txt": "2025-08-14 00:00:00"
    },
    {
      "dt": 1755140400,
      "main": {
        "temp": 15.26,
        "feels_like": 14.54,
        "temp_min": 15.26,
        "temp_max": 15.26,
        "pressure": 1019,
        "sea_level": 1019,
        "grnd_level": 1014,
        "humidity": 65,
        "temp_kf": 0
      },
      "weather": [
        {
          "id": 804,
          "main": "Clouds",
          "description": "mulet",
          "icon": "04n"
        }
      ],
      "clouds": {
        "all": 100
      },
      "wind": {
        "speed": 4.42,
        "deg": 118,
        "gust": 11.69
      },
      "visibility": 10000,
      "pop": 0,
      "sys": {
        "pod": "n"
      },
      "dt_txt": "2025-08-14 03:00:00"
    },
    {
      "dt": 1755151200,
      "main": {
        "temp": 17.94,
        "feels_like": 17.62,
        "temp_min": 17.94,
        "temp_max": 17.94,
        "pressure": 1019,
        "sea_level": 1019,
        "grnd_level": 1014,
        "humidity": 70,
        "temp_kf": 0
      },
      "weather": [
        {
          "id": 500,
          "main": "Rain",
          "description": "lätt regn",
          "icon": "10d"
        }
      ],
      "clouds": {
        "all": 100
      },
      "wind": {
        "speed": 4.86,
        "deg": 121,
        "gust": 11.69
      },
      "visibility": 10000,
      "pop": 0.2,
      "rain": {
        "3h": 0.12
      },
      "sys": {
        "pod": "d"
      },
      "dt_txt": "2025-08-14 06:00:00"
    },
    {
      "dt": 1755162000,
      "main": {
        "temp": 23.6,
        "feels_like": 23.5,
        "temp_min": 23.6,
        "temp_max": 23.6,
        "pressure": 1019,
        "sea_level": 1019,
        "grnd_level": 1014,
        "humidity": 57,
        "temp_kf": 0
      },
      "weather": [
        {
          "id": 500,
          "main": "Rain",
          "description": "lätt regn",
          "icon": "10d"
        }
      ],
      "clouds": {
        "all": 99
      },
      "wind": {
        "speed": 4.77,
        "deg": 159,
        "gust": 9.37
      },
      "visibility": 10000,
      "pop": 0.45,
      "rain": {
        "3h": 0.29
      },
      "sys": {
        "pod": "d"
      },
      "dt_txt": "2025-08-14 09:00:00"
    },
    {
      "dt": 1755172800,
      "main": {
        "temp": 24.51,
        "feels_like": 24.53,
        "temp_min": 24.51,
        "temp_max": 24.51,
        "pressure": 1019,
        "sea_level": 1019,
        "grnd_level": 1013,
        "humidity": 58,
        "temp_kf": 0
      },
      "weather": [
        {
          "id": 500,
          "main": "Rain",
          "description": "lätt regn",
          "icon": "10d"
        }
      ],
      "clouds": {
        "all": 100
      },
      "wind": {
        "speed": 5.37,
        "deg": 197,
        "gust": 10.03
      },
      "visibility": 10000,
      "pop": 0.2,
      "rain": {
        "3h": 0.15
      },
      "sys": {
        "pod": "d"
      },
      "dt_txt": "2025-08-14 12:00:00"
    },
    {
      "dt": 1755183600,
      "main": {
        "temp": 18.85,
        "feels_like": 19.09,
        "temp_min": 18.85,
        "temp_max": 18.85,
        "pressure": 1018,
        "sea_level": 1018,
        "grnd_level": 1013,
        "humidity": 88,
        "temp_kf": 0
      },
      "weather": [
        {
          "id": 500,
          "main": "Rain",
          "description": "lätt regn",
          "icon": "10d"
        }
      ],
      "clouds": {
        "all": 100
      },
      "wind": {
        "speed": 5.2,
        "deg": 137,
        "gust": 12.15
      },
      "visibility": 10000,
      "pop": 1,
      "rain": {
        "3h": 1.85
      },
      "sys": {
        "pod": "d"
      },
      "dt_txt": "2025-08-14 15:00:00"
    },
    {
      "dt": 1755194400,
      "main": {
        "temp": 20.58,
        "feels_like": 20.78,
        "temp_min": 20.58,
        "temp_max": 20.58,
        "pressure": 1017,
        "sea_level": 1017,
        "grnd_level": 1012,
        "humidity": 80,
        "temp_kf": 0
      },
      "weather": [
        {
          "id": 500,
          "main": "Rain",
          "description": "lätt regn",
          "icon": "10d"
        }
      ],
      "clouds": {
        "all": 95
      },
      "wind": {
        "speed": 3.79,
        "deg": 159,
        "gust": 10.3
      },
      "visibility": 10000,
      "pop": 1,
      "rain": {
        "3h": 0.36
      },
      "sys": {
        "pod": "d"
      },
      "dt_txt": "2025-08-14 18:00:00"
    },
    {
      "dt": 1755205200,
      "main": {
        "temp": 18.12,
        "feels_like": 18.31,
        "temp_min": 18.12,
        "temp_max": 18.12,
        "pressure": 1017,
        "sea_level": 1017,
        "grnd_level": 1012,
        "humidity": 89,
        "temp_kf": 0
      },
      "weather": [
        {
          "id": 500,
          "main": "Rain",
          "description": "lätt regn",
          "icon": "10n"
        }
      ],
      "clouds": {
        "all": 85
      },
      "wind": {
        "speed": 2.62,
        "deg": 143,
        "gust": 7.77
      },
      "visibility": 10000,
      "pop": 0.94,
      "rain": {
        "3h": 0.58
      },
      "sys": {
        "pod": "n"
      },
      "dt_txt": "2025-08-14 21:00:00"
    },
    {
      "dt": 1755216000,
      "main": {
        "temp": 16.67,
        "feels_like": 16.74,
        "temp_min": 16.67,
        "temp_max": 16.67,
        "pressure": 1016,
        "sea_level": 1016,
        "grnd_level": 1010,
        "humidity": 90,
        "temp_kf": 0
      },
      "weather": [
        {
          "id": 500,
          "main": "Rain",
          "description": "lätt regn",
          "icon": "10n"
        }
      ],
      "clouds": {
        "all": 93
      },
      "wind": {
        "speed": 3.55,
        "deg": 130,
        "gust": 11.57
      },
      "visibility": 10000,
      "pop": 1,
      "rain": {
        "3h": 0.82
      },
      "sys": {
        "pod": "n"
      },
      "dt_txt": "2025-08-15 00:00:00"
    },
    {
      "dt": 1755226800,
      "main": {
        "temp": 17.12,
        "feels_like": 17.29,
        "temp_min": 17.12,
        "temp_max": 17.12,
        "pressure": 1013,
        "sea_level": 1013,
        "grnd_level": 1008,
        "humidity": 92,
        "temp_kf": 0
      },
      "weather": [
        {
          "id": 500,
          "main": "Rain",
          "description": "lätt regn",
          "icon": "10n"
        }
      ],
      "clouds": {
        "all": 100
      },
      "wind": {
        "speed": 4.67,
        "deg": 162,
        "gust": 10.48
      },
      "visibility": 10000,
      "pop": 1,
      "rain": {
        "3h": 0.73
      },
      "sys": {
        "pod": "n"
      },
      "dt_txt": "2025-08-15 03:00:00"
    },
    {
      "dt": 1755237600,
      "main": {
        "temp": 18.31,
        "feels_like": 18.68,
        "temp_min": 18.31,
        "temp_max": 18.31,
        "pressure": 1013,
        "sea_level": 1013,
        "grnd_level": 1007,
        "humidity": 95,
        "temp_kf": 0
      },
      "weather": [
        {
          "id": 500,
          "main": "Rain",
          "description": "lätt regn",
          "icon": "10d"
        }
      ],
      "clouds": {
        "all": 100
      },
      "wind": {
        "speed": 4.18,
        "deg": 192,
        "gust": 6.81
      },
      "visibility": 10000,
      "pop": 1,
      "rain": {
        "3h": 0.82
      },
      "sys": {
        "pod": "d"
      },
      "dt_txt": "2025-08-15 06:00:00"
    },
    {
      "dt": 1755248400,
      "main": {
        "temp": 19.67,
        "feels_like": 19.78,
        "temp_min": 19.67,
        "temp_max": 19.67,
        "pressure": 1013,
        "sea_level": 1013,
        "grnd_level": 1008,
        "humidity": 80,
        "temp_kf": 0
      },
      "weather": [
        {
          "id": 804,
          "main": "Clouds",
          "description": "mulet",
          "icon": "04d"
        }
      ],
      "clouds": {
        "all": 87
      },
      "wind": {
        "speed": 4.28,
        "deg": 249,
        "gust": 6.92
      },
      "visibility": 10000,
      "pop": 0,
      "sys": {
        "pod": "d"
      },
      "dt_txt": "2025-08-15 09:00:00"
    },
    {
      "dt": 1755259200,
      "main": {
        "temp": 21.35,
        "feels_like": 21.34,
        "temp_min": 21.35,
        "temp_max": 21.35,
        "pressure": 1013,
        "sea_level": 1013,
        "grnd_level": 1008,
        "humidity": 69,
        "temp_kf": 0
      },
      "weather": [
        {
          "id": 802,
          "main": "Clouds",
          "description": "växlande molnighet",
          "icon": "03d"
        }
      ],
      "clouds": {
        "all": 46
      },
      "wind": {
        "speed": 4.97,
        "deg": 229,
        "gust": 9.06
      },
      "visibility": 10000,
      "pop": 0,
      "sys": {
        "pod": "d"
      },
      "dt_txt": "2025-08-15 12:00:00"
    }
  ],
  "city": {
    "id": 2711537,
    "name": "Gothenburg",
    "coord": {
      "lat": 57.7072,
      "lon": 11.9668
    },
    "country": "SE",
    "population": 504084,
    "timezone": 7200,
    "sunrise": 1754796363,
    "sunset": 1754852943
  }
}