{
  "cod": "200",
  "message": 0,
  "cnt": 40,
  "list": [
    {
      "dt": 1762030800,
      "main": {
        "temp": 4.27,
        "feels_like": 1.45,
        "temp_min": 4.27,
        "temp_max": 4.88,
        "pressure": 1014,
        "sea_level": 1014,
        "grnd_level": 1007,
        "humidity": 92,
        "temp_kf": -0.61
      },
      "weather": [
        {
          "id": 803,
          "main": "Clouds",
          "description": "molnigt",
          "icon": "04n"
        }
      ],
      "clouds": {
        "all": 78
      },
      "wind": {
        "speed": 3.24,
        "deg": 172,
        "gust": 7.6
      },
      "visibility": 10000,
      "pop": 0,
      "sys": {
        "pod": "n"
      },
      "dt_txt": "2025-11-01 21:00:00"
    },
    {
      "dt": 1762041600,
      "main": {
        "temp": 5.21,
        "feels_like": 1.47,
        "temp_min": 5.21,
        "temp_max": 5.83,
        "pressure": 1012,
        "sea_level": 1012,
        "grnd_level": 1005,
        "humidity": 92,
        "temp_kf": -0.62
      },
      "weather": [
        {
          "id": 803,
          "main": "Clouds",
          "description": "molnigt",
          "icon": "04n"
        }
      ],
      "clouds": {
        "all": 76
      },
      "wind": {
        "speed": 5.27,
        "deg": 160,
        "gust": 10.29
      },
      "visibility": 10000,
      "pop": 0,
      "sys": {
        "pod": "n"
      },
      "dt_txt": "2025-11-02 00:00:00"
    },
    {
      "dt": 1762052400,
      "main": {
        "temp": 5.22,
        "feels_like": 1.63,
        "temp_min": 5.22,
        "temp_max": 5.22,
        "pressure": 1008,
        "sea_level": 1008,
        "grnd_level": 1002,
        "humidity": 91,
        "temp_kf": 0
      },
      "weather": [
        {
          "id": 804,
          "main": "Clouds",
          "description": "mulet",
          "icon": "04n"
        }
      ],
      "clouds": {
        "all": 100
      },
      "wind": {
        "speed": 4.96,
        "deg": 145,
        "gust": 10.42
      },
      "visibility": 10000,
      "pop": 0,
      "sys": {
        "pod": "n"
      },
      "dt_txt": "2025-11-02 03:00:00"
    },
    {
      "dt": 1762063200,
      "main": {
        "temp": 5.2,
        "feels_like": 1.69,
        "temp_min": 5.2,
        "temp_max": 5.2,
        "pressure": 1005,
        "sea_level": 1005,
        "grnd_level": 999,
        "humidity": 92,
        "temp_kf": 0
      },
      "weather": [
        {
          "id": 804,
          "main": "Clouds",
          "description": "mulet",
          "icon": "04n"
        }
      ],
      "clouds": {
        "all": 100
      },
      "wind": {
        "speed": 4.78,
        "deg": 143,
        "gust": 8.85
      },
      "visibility": 10000,
      "pop": 0,
      "sys": {
        "pod": "n"
      },
      "dt_txt": "2025-11-02 06:00:00"
    },
    {
      "dt": 1762074000,
      "main": {
        "temp": 5.4,
        "feels_like": 1.42,
        "temp_min": 5.4,
        "temp_max": 5.4,
        "pressure": 1003,
        "sea_level": 1003,
        "grnd_level": 997,
        "humidity": 95,
        "temp_kf": 0
      },
      "weather": [
        {
          "id": 500,
          "main": "Rain",
          "description": "lätt regn",
          "icon": "10d"
        }
      ],
      "clouds": {
        "all": 100
      },
      "wind": {
        "speed": 5.97,
        "deg": 127,
        "gust": 12.41
      },
      "visibility": 8244,
      "pop": 1,
      "rain": {
        "3h": 1.15
      },
      "sys": {
        "pod": "d"
      },
      "dt_txt": "2025-11-02 09:00:00"
    },
    {
      "dt": 1762084800,
      "main": {
        "temp": 7.08,
        "feels_like": 4.15,
        "temp_min": 7.08,
        "temp_max": 7.08,
        "pressure": 1000,
        "sea_level": 1000,
        "grnd_level": 994,
        "humidity": 96,
        "temp_kf": 0
      },
      "weather": [
        {
          "id": 500,
          "main": "Rain",
          "description": "lätt regn",
          "icon": "10d"
        }
      ],
      "clouds": {
        "all": 100
      },
      "wind": {
        "speed": 4.53,
        "deg": 192,
        "gust": 10.55
      },
      "visibility": 8687,
      "pop": 1,
      "rain": {
        "3h": 1.41
      },
      "sys": {
        "pod": "d"
      },
      "dt_txt": "2025-11-02 12:00:00"
    },
    {
      "dt": 1762095600,
      "main": {
        "temp": 7.23,
        "feels_like": 4.81,
        "temp_min": 7.23,
        "temp_max": 7.23,
        "pressure": 1001,
        "sea_level": 1001,
        "grnd_level": 995,
        "humidity": 93,
        "temp_kf": 0
      },
      "weather": [
        {
          "id": 804,
          "main": "Clouds",
          "description": "mulet",
          "icon": "04n"
        }
      ],
      "clouds": {
        "all": 97
      },
      "wind": {
        "speed": 3.61,
        "deg": 229,
        "gust": 8.97
      },
      "visibility": 10000,
      "pop": 0,
      "sys": {
        "pod": "n"
      },
      "dt_txt": "2025-11-02 15:00:00"
    },
    {
      "dt": 1762106400,
      "main": {
        "temp": 4.86,
        "feels_like": 2.86,
        "temp_min": 4.86,
        "temp_max": 4.86,
        "pressure": 1003,
        "sea_level": 1003,
        "grnd_level": 997,
        "humidity": 94,
        "temp_kf": 0
      },
      "weather": [
        {
          "id": 803,
          "main": "Clouds",
          "description": "molnigt",
          "icon": "04n"
        }
      ],
      "clouds": {
        "all": 70
      },
      "wind": {
        "speed": 2.36,
        "deg": 235,
        "gust": 3.84
      },
      "visibility": 10000,
      "pop": 0,
      "sys": {
        "pod": "n"
      },
      "dt_txt": "2025-11-02 18:00:00"
    },
    {
      "dt": 1762117200,
      "main": {
        "temp": 3.92,
        "feels_like": 3.92,
        "temp_min": 3.92,
        "temp_max": 3.92,
        "pressure": 1004,
        "sea_level": 1004,
        "grnd_level": 997,
        "humidity": 91,
        "temp_kf": 0
      },
      "weather": [
        {
          "id": 802,
          "main": "Clouds",
          "description": "växlande molnighet",
          "icon": "03n"
        }
      ],
      "clouds": {
        "all": 36
      },
      "wind": {
        "speed": 1.22,
        "deg": 281,
        "gust": 1.21
      },
      "visibility": 10000,
      "pop": 0,
      "sys": {
        "pod": "n"
      },
      "dt_txt": "2025-11-02 21:00:00"
    },
    {
      "dt": 1762128000,
      "main": {
        "temp": 3.81,
        "feels_like": 3.81,
        "temp_min": 3.81,
        "temp_max": 3.81,
        "pressure": 1004,
        "sea_level": 1004,
        "grnd_level": 998,
        "humidity": 91,
        "temp_kf": 0
      },
      "weather": [
        {
          "id": 803,
          "main": "Clouds",
          "description": "molnigt",
          "icon": "04n"
        }
      ],
      "clouds": {
        "all": 68
      },
      "wind": {
        "speed": 0.84,
        "deg": 323,
        "gust": 0.81
      },
      "visibility": 10000,
      "pop": 0,
      "sys": {
        "pod": "n"
      },
      "dt_txt": "2025-11-03 00:00:00"
    },
    {
      "dt": 1762138800,
      "main": {
        "temp": 3.49,
        "feels_like": 3.49,
        "temp_min": 3.49,
        "temp_max": 3.49,
        "pressure": 1003,
        "sea_level": 1003,
        "grnd_level": 997,
        "humidity": 92,
        "temp_kf": 0
      },
      "weather": [
        {
          "id": 804,
          "main": "Clouds",
          "description": "mulet",
          "icon": "04n"
        }
      ],
      "clouds": {
        "all": 100
      },
      "wind": {
        "speed": 0.6,
        "deg": 18,
        "gust": 0.62
      },
      "visibility": 10000,
      "pop": 0,
      "sys": {
        "pod": "n"
      },
      "dt_txt": "2025-11-03 03:00:00"
    },
    {
      "dt": 1762149600,
      "main": {
        "temp": 3.51,
        "feels_like": 2.21,
        "temp_min": 3.51,
        "temp_max": 3.51,
        "pressure": 1002,
        "sea_level": 1002,
        "grnd_level": 996,
        "humidity": 93,
        "temp_kf": 0
      },
      "weather": [
        {
          "id": 804,
          "main": "Clouds",
          "description": "mulet",
          "icon": "04n"
        }
      ],
      "clouds": {
        "all": 100
      },
      "wind": {
        "speed": 1.53,
        "deg": 19,
        "gust": 1.57
      },
      "visibility": 10000,
      "pop": 0,
      "sys": {
        "pod": "n"
      },
      "dt_txt": "2025-11-03 06:00:00"
    },
    {
      "dt": 1762160400,
      "main": {
        "temp": 4.09,
        "feels_like": 2.18,
        "temp_min": 4.09,
        "temp_max": 4.09,
        "pressure": 1002,
        "sea_level": 1002,
        "grnd_level": 996,
        "humidity": 96,
        "temp_kf": 0
      },
      "weather": [
        {
          "id": 501,
          "main": "Rain",
          "description": "något regn",
          "icon": "10d"
        }
      ],
      "clouds": {
        "all": 100
      },
      "wind": {
        "speed": 2.12,
        "deg": 341,
        "gust": 3.44
      },
      "visibility": 10000,
      "pop": 1,
      "rain": {
        "3h": 3.3
      },
      "sys": {
        "pod": "d"
      },
      "dt_txt": "2025-11-03 09:00:00"
    },
    {
      "dt": 1762171200,
      "main": {
        "temp": 4.57,
        "feels_like": 2.22,
        "temp_min": 4.57,
        "temp_max": 4.57,
        "pressure": 1002,
        "sea_level": 1002,
        "grnd_level": 996,
        "humidity": 93,
        "temp_kf": 0
      },
      "weather": [
        {
          "id": 500,
          "main": "Rain",
          "description": "lätt regn",
          "icon": "10d"
        }
      ],
      "clouds": {
        "all": 100
      },
      "wind": {
        "speed": 2.7,
        "deg": 268,
        "gust": 5.68
      },
      "visibility": 10000,
      "pop": 1,
      "rain": {
        "3h": 0.53
      },
      "sys": {
        "pod": "d"
      },
      "dt_txt": "2025-11-03 12:00:00"
    },
    {
      "dt": 1762182000,
      "main": {
        "temp": 4.25,
        "feels_like": 3.17,
        "temp_min": 4.25,
        "temp_max": 4.25,
        "pressure": 1003,
        "sea_level": 1003,
        "grnd_level": 997,
        "humidity": 96,
        "temp_kf": 0
      },
      "weather": [
        {
          "id": 804,
          "main": "Clouds",
          "description": "mulet",
          "icon": "04n"
        }
      ],
      "clouds": {
        "all": 100
      },
      "wind": {
        "speed": 1.44,
        "deg": 263,
        "gust": 3.62
      },
      "visibility": 10000,
      "pop": 0,
      "sys": {
        "pod": "n"
      },
      "dt_txt": "2025-11-03 15:00:00"
    },
    {
      "dt": 1762192800,
      "main": {
        "temp": 3.43,
        "feels_like": 3.43,
        "temp_min": 3.43,
        "temp_max": 3.43,
        "pressure": 1003,
        "sea_level": 1003,
        "grnd_level": 997,
        "humidity": 95,
        "temp_kf": 0
      },
      "weather": [
        {
          "id": 804,
          "main": "Clouds",
          "description": "mulet",
          "icon": "04n"
        }
      ],
      "clouds": {
        "all": 95
      },
      "wind": {
        "speed": 0.52,
        "deg": 267,
        "gust": 0.46
      },
      "visibility": 10000,
      "pop": 0,
      "sys": {
        "pod": "n"
      },
      "dt_txt": "2025-11-03 18:00:00"
    },
    {
      "dt": 1762203600,
      "main": {
        "temp": 2.65,
        "feels_like": 2.65,
        "temp_min": 2.65,
        "temp_max": 2.65,
        "pressure": 1003,
        "sea_level": 1003,
        "grnd_level": 997,
        "humidity": 96,
        "temp_kf": 0
      },
      "weather": [
        {
          "id": 801,
          "main": "Clouds",
          "description": "lätt molnighet",
          "icon": "02n"
        }
      ],
      "clouds": {
        "all": 24
      },
      "wind": {
        "speed": 0.85,
        "deg": 336,
        "gust": 0.55
      },
      "visibility": 10000,
      "pop": 0,
      "sys": {
        "pod": "n"
      },
      "dt_txt": "2025-11-03 21:00:00"
    },
    {
      "dt": 1762214400,
      "main": {
        "temp": 1.94,
        "feels_like": 1.94,
        "temp_min": 1.94,
        "temp_max": 1.94,
        "pressure": 1004,
        "sea_level": 1004,
        "grnd_level": 998,
        "humidity": 96,
        "temp_kf": 0
      },
      "weather": [
        {
          "id": 801,
          "main": "Clouds",
          "description": "lätt molnighet",
          "icon": "02n"
        }
      ],
      "clouds": {
        "all": 22
      },
      "wind": {
        "speed": 1.1,
        "deg": 309,
        "gust": 0.91
      },
      "visibility": 10000,
      "pop": 0,
      "sys": {
        "pod": "n"
      },
      "dt_txt": "2025-11-04 00:00:00"
    },
    {
      "dt": 1762225200,
      "main": {
        "temp": 1.34,
        "feels_like": 1.34,
        "temp_min": 1.34,
        "temp_max": 1.34,
        "pressure": 1004,
        "sea_level": 1004,
        "grnd_level": 998,
        "humidity": 95,
        "temp_kf": 0
      },
      "weather": [
        {
          "id": 801,
          "main": "Clouds",
          "description": "lätt molnighet",
          "icon": "02n"
        }
      ],
      "clouds": {
        "all": 12
      },
      "wind": {
        "speed": 1.17,
        "deg": 288,
        "gust": 1.14
      },
      "visibility": 10000,
      "pop": 0,
      "sys": {
        "pod": "n"
      },
      "dt_txt": "2025-11-04 03:00:00"
    },
    {
      "dt": 1762236000,
      "main": {
        "temp": 1.22,
        "feels_like": 1.22,
        "temp_min": 1.22,
        "temp_max": 1.22,
        "pressure": 1004,
        "sea_level": 1004,
        "grnd_level": 998,
        "humidity": 95,
        "temp_kf": 0
      },
      "weather": [
        {
          "id": 802,
          "main": "Clouds",
          "description": "växlande molnighet",
          "icon": "03n"
        }
      ],
      "clouds": {
        "all": 27
      },
      "wind": {
        "speed": 0.62,
        "deg": 171,
        "gust": 0.84
      },
      "visibility": 10000,
      "pop": 0,
      "sys": {
        "pod": "n"
      },
      "dt_txt": "2025-11-04 06:00:00"
    },
    {
      "dt": 1762246800,
      "main": {
        "temp": 4.62,
        "feels_like": 2.14,
        "temp_min": 4.62,
        "temp_max": 4.62,
        "pressure": 1004,
        "sea_level": 1004,
        "grnd_level": 998,
        "humidity": 93,
        "temp_kf": 0
      },
      "weather": [
        {
          "id": 804,
          "main": "Clouds",
          "description": "mulet",
          "icon": "04d"
        }
      ],
      "clouds": {
        "all": 91
      },
      "wind": {
        "speed": 2.88,
        "deg": 206,
        "gust": 8.59
      },
      "visibility": 10000,
      "pop": 0,
      "sys": {
        "pod": "d"
      },
      "dt_txt": "2025-11-04 09:00:00"
    },
    {
      "dt": 1762257600,
      "main": {
        "temp": 6.51,
        "feels_like": 3.36,
        "temp_min": 6.51,
        "temp_max": 6.51,
        "pressure": 1003,
        "sea_level": 1003,
        "grnd_level": 997,
        "humidity": 97,
        "temp_kf": 0
      },
      "weather": [
        {
          "id": 500,
          "main": "Rain",
          "description": "lätt regn",
          "icon": "10d"
        }
      ],
      "clouds": {
        "all": 95
      },
      "wind": {
        "speed": 4.7,
        "deg": 192,
        "gust": 11.27
      },
      "visibility": 9128,
      "pop": 0.2,
      "rain": {
        "3h": 0.41
      },
      "sys": {
        "pod": "d"
      },
      "dt_txt": "2025-11-04 12:00:00"
    },
    {
      "dt": 1762268400,
      "main": {
        "temp": 6.43,
        "feels_like": 3.85,
        "temp_min": 6.43,
        "temp_max": 6.43,
        "pressure": 1002,
        "sea_level": 1002,
        "grnd_level": 996,
        "humidity": 98,
        "temp_kf": 0
      },
      "weather": [
        {
          "id": 804,
          "main": "Clouds",
          "description": "mulet",
          "icon": "04n"
        }
      ],
      "clouds": {
        "all": 100
      },
      "wind": {
        "speed": 3.58,
        "deg": 201,
        "gust": 8.05
      },
      "visibility": 4957,
      "pop": 0,
      "sys": {
        "pod": "n"
      },
      "dt_txt": "2025-11-04 15:00:00"
    },
    {
      "dt": 1762279200,
      "main": {
        "temp": 5.99,
        "feels_like": 4.68,
        "temp_min": 5.99,
        "temp_max": 5.99,
        "pressure": 1002,
        "sea_level": 1002,
        "grnd_level": 996,
        "humidity": 98,
        "temp_kf": 0
      },
      "weather": [
        {
          "id": 500,
          "main": "Rain",
          "description": "lätt regn",
          "icon": "10n"
        }
      ],
      "clouds": {
        "all": 100
      },
      "wind": {
        "speed": 1.84,
        "deg": 227,
        "gust": 4.39
      },
      "visibility": 10000,
      "pop": 0.22,
      "rain": {
        "3h": 0.35
      },
      "sys": {
        "pod": "n"
      },
      "dt_txt": "2025-11-04 18:00:00"
    },
    {
      "dt": 1762290000,
      "main": {
        "temp": 5.98,
        "feels_like": 4.65,
        "temp_min": 5.98,
        "temp_max": 5.98,
        "pressure": 1002,
        "sea_level": 1002,
        "grnd_level": 996,
        "humidity": 97,
        "temp_kf": 0
      },
      "weather": [
        {
          "id": 804,
          "main": "Clouds",
          "description": "mulet",
          "icon": "04n"
        }
      ],
      "clouds": {
        "all": 96
      },
      "wind": {
        "speed": 1.86,
        "deg": 243,
        "gust": 2.22
      },
      "visibility": 10000,
      "pop": 0,
      "sys": {
        "pod": "n"
      },
      "dt_txt": "2025-11-04 21:00:00"
    },
    {
      "dt": 1762300800,
      "main": {
        "temp": 5.75,
        "feels_like": 4.32,
        "temp_min": 5.75,
        "temp_max": 5.75,
        "pressure": 1002,
        "sea_level": 1002,
        "grnd_level": 996,
        "humidity": 95,
        "temp_kf": 0
      },
      "weather": [
        {
          "id": 804,
          "main": "Clouds",
          "description": "mulet",
          "icon": "04n"
        }
      ],
      "clouds": {
        "all": 98
      },
      "wind": {
        "speed": 1.92,
        "deg": 243,
        "gust": 2.46
      },
      "visibility": 10000,
      "pop": 0,
      "sys": {
        "pod": "n"
      },
      "dt_txt": "2025-11-05 00:00:00"
    },
    {
      "dt": 1762311600,
      "main": {
        "temp": 5.93,
        "feels_like": 5.19,
        "temp_min": 5.93,
        "temp_max": 5.93,
        "pressure": 1001,
        "sea_level": 1001,
        "grnd_level": 995,
        "humidity": 97,
        "temp_kf": 0
      },
      "weather": [
        {
          "id": 804,
          "main": "Clouds",
          "description": "mulet",
          "icon": "04n"
        }
      ],
      "clouds": {
        "all": 100
      },
      "wind": {
        "speed": 1.36,
        "deg": 230,
        "gust": 2.28
      },
      "visibility": 10000,
      "pop": 0,
      "sys": {
        "pod": "n"
      },
      "dt_txt": "2025-11-05 03:00:00"
    },
    {
      "dt": 1762322400,
      "main": {
        "temp": 6.89,
        "feels_like": 5.33,
        "temp_min": 6.89,
        "temp_max": 6.89,
        "pressure": 1001,
        "sea_level": 1001,
        "grnd_level": 995,
        "humidity": 96,
        "temp_kf": 0
      },
      "weather": [
        {
          "id": 804,
          "main": "Clouds",
          "description": "mulet",
          "icon": "04n"
        }
      ],
      "clouds": {
        "all": 100
      },
      "wind": {
        "speed": 2.27,
        "deg": 244,
        "gust": 6.92
      },
      "visibility": 10000,
      "pop": 0,
      "sys": {
        "pod": "n"
      },
      "dt_txt": "2025-11-05 06:00:00"
    },
    {
      "dt": 1762333200,
      "main": {
        "temp": 7.31,
        "feels_like": 5.69,
        "temp_min": 7.31,
        "temp_max": 7.31,
        "pressure": 1002,
        "sea_level": 1002,
        "grnd_level": 996,
        "humidity": 93,
        "temp_kf": 0
      },
      "weather": [
        {
          "id": 804,
          "main": "Clouds",
          "description": "mulet",
          "icon": "04d"
        }
      ],
      "clouds": {
        "all": 100
      },
      "wind": {
        "speed": 2.43,
        "deg": 259,
        "gust": 7.98
      },
      "visibility": 10000,
      "pop": 0,
      "sys": {
        "pod": "d"
      },
      "dt_txt": "2025-11-05 09:00:00"
    },
    {
      "dt": 1762344000,
      "main": {
        "temp": 8.16,
        "feels_like": 6.58,
        "temp_min": 8.16,
        "temp_max": 8.16,
        "pressure": 1003,
        "sea_level": 1003,
        "grnd_level": 997,
        "humidity": 86,
        "temp_kf": 0
      },
      "weather": [
        {
          "id": 803,
          "main": "Clouds",
          "description": "molnigt",
          "icon": "04d"
        }
      ],
      "clouds": {
        "all": 80
      },
      "wind": {
        "speed": 2.59,
        "deg": 272,
        "gust": 7.78
      },
      "visibility": 10000,
      "pop": 0,
      "sys": {
        "pod": "d"
      },
      "dt_txt": "2025-11-05 12:00:00"
    },
    {
      "dt": 1762354800,
      "main": {
        "temp": 6.78,
        "feels_like": 4.95,
        "temp_min": 6.78,
        "temp_max": 6.78,
        "pressure": 1005,
        "sea_level": 1005,
        "grnd_level": 999,
        "humidity": 89,
        "temp_kf": 0
      },
      "weather": [
        {
          "id": 803,
          "main": "Clouds",
          "description": "molnigt",
          "icon": "04n"
        }
      ],
      "clouds": {
        "all": 54
      },
      "wind": {
        "speed": 2.57,
        "deg": 264,
        "gust": 7.16
      },
      "visibility": 10000,
      "pop": 0,
      "sys": {
        "pod": "n"
      },
      "dt_txt": "2025-11-05 15:00:00"
    },
    {
      "dt": 1762365600,
      "main": {
        "temp": 6.37,
        "feels_like": 4.61,
        "temp_min": 6.37,
        "temp_max": 6.37,
        "pressure": 1007,
        "sea_level": 1007,
        "grnd_level": 1001,
        "humidity": 87,
        "temp_kf": 0
      },
      "weather": [
        {
          "id": 802,
          "main": "Clouds",
          "description": "växlande molnighet",
          "icon": "03n"
        }
      ],
      "clouds": {
        "all": 33
      },
      "wind": {
        "speed": 2.39,
        "deg": 276,
        "gust": 5.79
      },
      "visibility": 10000,
      "pop": 0,
      "sys": {
        "pod": "n"
      },
      "dt_txt": "2025-11-05 18:00:00"
    },
    {
      "dt": 1762376400,
      "main": {
        "temp": 5.85,
        "feels_like": 4.51,
        "temp_min": 5.85,
        "temp_max": 5.85,
        "pressure": 1009,
        "sea_level": 1009,
        "grnd_level": 1002,
        "humidity": 89,
        "temp_kf": 0
      },
      "weather": [
        {
          "id": 804,
          "main": "Clouds",
          "description": "mulet",
          "icon": "04n"
        }
      ],
      "clouds": {
        "all": 86
      },
      "wind": {
        "speed": 1.85,
        "deg": 239,
        "gust": 1.02
      },
      "visibility": 10000,
      "pop": 0,
      "sys": {
        "pod": "n"
      },
      "dt_txt": "2025-11-05 21:00:00"
    },
    {
      "dt": 1762387200,
      "main": {
        "temp": 5.49,
        "feels_like": 4.04,
        "temp_min": 5.49,
        "temp_max": 5.49,
        "pressure": 1010,
        "sea_level": 1010,
        "grnd_level": 1003,
        "humidity": 89,
        "temp_kf": 0
      },
      "weather": [
        {
          "id": 804,
          "main": "Clouds",
          "description": "mulet",
          "icon": "04n"
        }
      ],
      "clouds": {
        "all": 90
      },
      "wind": {
        "speed": 1.9,
        "deg": 247,
        "gust": 1.41
      },
      "visibility": 10000,
      "pop": 0,
      "sys": {
        "pod": "n"
      },
      "dt_txt": "2025-11-06 00:00:00"
    },
    {
      "dt": 1762398000,
      "main": {
        "temp": 5.98,
        "feels_like": 5.98,
        "temp_min": 5.98,
        "temp_max": 5.98,
        "pressure": 1009,
        "sea_level": 1009,
        "grnd_level": 1003,
        "humidity": 86,
        "temp_kf": 0
      },
      "weather": [
        {
          "id": 804,
          "main": "Clouds",
          "description": "mulet",
          "icon": "04n"
        }
      ],
      "clouds": {
        "all": 100
      },
      "wind": {
        "speed": 1.12,
        "deg": 276,
        "gust": 1.13
      },
      "visibility": 10000,
      "pop": 0,
      "sys": {
        "pod": "n"
      },
      "dt_txt": "2025-11-06 03:00:00"
    },
    {
      "dt": 1762408800,
      "main": {
        "temp": 6.12,
        "feels_like": 4.76,
        "temp_min": 6.12,
        "temp_max": 6.12,
        "pressure": 1009,
        "sea_level": 1009,
        "grnd_level": 1003,
        "humidity": 93,
        "temp_kf": 0
      },
      "weather": [
        {
          "id": 804,
          "main": "Clouds",
          "description": "mulet",
          "icon": "04n"
        }
      ],
      "clouds": {
        "all": 100
      },
      "wind": {
        "speed": 1.91,
        "deg": 160,
        "gust": 2.63
      },
      "visibility": 10000,
      "pop": 0,
      "sys": {
        "pod": "n"
      },
      "dt_txt": "2025-11-06 06:00:00"
    },
    {
      "dt": 1762419600,
      "main": {
        "temp": 7.49,
        "feels_like": 5.4,
        "temp_min": 7.49,
        "temp_max": 7.49,
        "pressure": 1008,
        "sea_level": 1008,
        "grnd_level": 1002,
        "humidity": 98,
        "temp_kf": 0
      },
      "weather": [
        {
          "id": 804,
          "main": "Clouds",
          "description": "mulet",
          "icon": "04d"
        }
      ],
      "clouds": {
        "all": 100
      },
      "wind": {
        "speed": 3.15,
        "deg": 181,
        "gust": 9.68
      },
      "visibility": 5835,
      "pop": 0,
      "sys": {
        "pod": "d"
      },
      "dt_txt": "2025-11-06 09:00:00"
    },
    {
      "dt": 1762430400,
      "main": {
        "temp": 7.82,
        "feels_like": 4.83,
        "temp_min": 7.82,
        "temp_max": 7.82,
        "pressure": 1006,
        "sea_level": 1006,
        "grnd_level": 1000,
        "humidity": 98,
        "temp_kf": 0
      },
      "weather": [
        {
          "id": 500,
          "main": "Rain",
          "description": "lätt regn",
          "icon": "10d"
        }
      ],
      "clouds": {
        "all": 100
      },
      "wind": {
        "speed": 5.08,
        "deg": 192,
        "gust": 12.54
      },
      "pop": 0.2,
      "rain": {
        "3h": 0.42
      },
      "sys": {
        "pod": "d"
      },
      "dt_txt": "2025-11-06 12:00:00"
    },
    {
      "dt": 1762441200,
      "main": {
        "temp": 8.2,
        "feels_like": 5.35,
        "temp_min": 8.2,
        "temp_max": 8.2,
        "pressure": 1005,
        "sea_level": 1005,
        "grnd_level": 999,
        "humidity": 98,
        "temp_kf": 0
      },
      "weather": [
        {
          "id": 500,
          "main": "Rain",
          "description": "lätt regn",
          "icon": "10n"
        }
      ],
      "clouds": {
        "all": 100
      },
      "wind": {
        "speed": 4.97,
        "deg": 199,
        "gust": 14.36
      },
      "pop": 0.2,
      "rain": {
        "3h": 0.12
      },
      "sys": {
        "pod": "n"
      },
      "dt_txt": "2025-11-06 15:00:00"
    },
    {
      "dt": 1762452000,
      "main": {
        "temp": 8.28,
        "feels_like": 5.37,
        "temp_min": 8.28,
        "temp_max": 8.28,
        "pressure": 1003,
        "sea_level": 1003,
        "grnd_level": 997,
        "humidity": 96,
        "temp_kf": 0
      },
      "weather": [
        {
          "id": 804,
          "main": "Clouds",
          "description": "mulet",
          "icon": "04n"
        }
      ],
      "clouds": {
        "all": 100
      },
      "wind": {
        "speed": 5.17,
        "deg": 201,
        "gust": 15.48
      },
      "visibility": 10000,
      "pop": 0,
      "sys": {
        "pod": "n"
      },
      "dt_txt": "2025-11-06 18:00:00"
    }
  ],
  "city": {
    "id": 602150,
    "name": "Umeå",
    "coord": {
      "lat": 63.8284,
      "lon": 20.2597
    },
    "country": "SE",
    "population": 74005,
    "timezone": 3600,
    "sunrise": 1761978006,
    "sunset": 1762007092
  }
}